[
    {
        "card_title": "Caduceus[Staff]",
        "item_basestat": "Stat/EffectAmountMaxHP %100MaxMP600CSPD %200Aggro %-50Short Range Damage %-40Invincible Aid (sec)3",
        "item_obtainfrom": "Sunken Treasure-",
        "item_prop": "Sell0 SpinaProcessunknown"
    },
    {
        "card_title": "Caduceus[Staff]",
        "item_basestat": "Stat/EffectAmountMaxHP %100MaxMP600CSPD %200Aggro %-50Short Range Damage %-40Invincible Aid (sec)3",
        "item_obtainfrom": "Sunken Treasure-",
        "item_prop": "Sell0 SpinaProcessunknown"
    },
    {
        "card_title": "Caduceus[Staff]",
        "item_basestat": "Stat/EffectAmountMaxHP %100MaxMP600CSPD %200Aggro %-50Short Range Damage %-40Invincible Aid (sec)3",
        "item_obtainfrom": "Sunken Treasure-",
        "item_prop": "Sell0 SpinaProcessunknown"
    },
    {
        "card_title": "Libra[Staff]",
        "item_basestat": "Stat/EffectAmountBase ATK1MATK %-50CSPD1000Base Stability %30",
        "item_obtainfrom": "[NPC]Blacksmith : ZaldoSofya City: Blacksmith",
        "item_prop": "Sell1 SpinaProcess2 Cloth"
    },
    {
        "card_title": "Rod[Staff]",
        "item_basestat": "Stat/EffectAmountBase ATK10Base Stability %60",
        "item_obtainfrom": "Pomum(Lv 3)Rakau Plains",
        "item_prop": "Sell1 SpinaProcess2 Wood"
    },
    {
        "card_title": "Rod[Staff]",
        "item_basestat": "Stat/EffectAmountBase ATK10Attack MP Recovery1Base Stability %60",
        "item_obtainfrom": "[NPC]Blacksmith : ZaldoSofya City: Blacksmith",
        "item_prop": "Sell1 SpinaProcess2 Wood"
    },
    {
        "card_title": "Rod[Staff]",
        "item_basestat": "Stat/EffectAmountBase ATK10Base Stability %60Potential15",
        "item_obtainfrom": "[Player]Smith Skill-",
        "item_prop": "Sell1 SpinaProcess2 Wood"
    },
    {
        "card_title": "Exorcism Arrow[Staff]",
        "item_basestat": "Stat/EffectAmountBase ATK17Magic Pierce %50Magic Resistance %30Base Stability %100Magic Barrier1000",
        "item_obtainfrom": "[NPC]Blacksmith : ZaldoSofya City: Blacksmith",
        "item_prop": "Sell1 SpinaProcess2 Mana"
    },
    {
        "card_title": "Wind Staff[Staff]",
        "item_basestat": "Stat/EffectAmountBase ATK17MATK %-5CSPD100Wind Element1Base Stability %60",
        "item_obtainfrom": "Nemico(Lv 11)Underground Ruins: B1",
        "item_prop": "Sell10 SpinaProcess5 Wood"
    },
    {
        "card_title": "Wind Staff[Staff]",
        "item_basestat": "Stat/EffectAmountBase ATK17MATK %-10CSPD200Wind Element1Base Stability %60",
        "item_obtainfrom": "[NPC]Blacksmith : ZaldoSofya City: Blacksmith",
        "item_prop": "Sell10 SpinaProcess5 Wood"
    },
    {
        "card_title": "Wind Staff[Staff]",
        "item_basestat": "Stat/EffectAmountBase ATK17Base Stability %60Potential16",
        "item_obtainfrom": "[Player]Smith Skill-",
        "item_prop": "Sell10 SpinaProcess5 Wood"
    },
    {
        "card_title": "Mage Rod[Staff]",
        "item_basestat": "Stat/EffectAmountBase ATK25MaxMP50Aggro %-5Base Stability %60",
        "item_obtainfrom": "Roar(Lv 21)Ruined Temple: Area 2",
        "item_prop": "Sell20 SpinaProcess10 Metal"
    },
    {
        "card_title": "Mage Rod[Staff]",
        "item_basestat": "Stat/EffectAmountBase ATK25MaxMP100Base Stability %60",
        "item_obtainfrom": "[NPC]Blacksmith : ZaldoSofya City: Blacksmith",
        "item_prop": "Sell20 SpinaProcess10 Metal"
    },
    {
        "card_title": "Mage Rod[Staff]",
        "item_basestat": "Stat/EffectAmountBase ATK25Base Stability %60Potential18",
        "item_obtainfrom": "[Player]Smith Skill-",
        "item_prop": "Sell20 SpinaProcess10 Metal"
    },
    {
        "card_title": "1st Anniv Staff[Staff]",
        "item_basestat": "Stat/EffectAmountBase ATK29INT %1MaxMP100MATK %1Physical Resistance %6Base Stability %60",
        "item_obtainfrom": "[NPC]Blacksmith : ZaldoSofya City: Blacksmith",
        "item_prop": "Sell25 SpinaProcess12 Wood"
    },
    {
        "card_title": "1st Anniv Staff[Staff]",
        "item_basestat": "Stat/EffectAmountBase ATK29Base Stability %60Potential19",
        "item_obtainfrom": "[Player]Smith Skill-",
        "item_prop": "Sell25 SpinaProcess12 Wood"
    },
    {
        "card_title": "2nd Anniv Staff[Staff]",
        "item_basestat": "Stat/EffectAmountBase ATK29INT %1MaxMP100MATK %1Physical Resistance %6Base Stability %60",
        "item_obtainfrom": "[NPC]Blacksmith : ZaldoSofya City: Blacksmith",
        "item_prop": "Sell25 SpinaProcess12 Wood"
    },
    {
        "card_title": "2nd Anniv Staff[Staff]",
        "item_basestat": "Stat/EffectAmountBase ATK29Base Stability %60Potential19",
        "item_obtainfrom": "[Player]Smith Skill-",
        "item_prop": "Sell25 SpinaProcess12 Wood"
    },
    {
        "card_title": "3rd Anniv Staff[Staff]",
        "item_basestat": "Stat/EffectAmountBase ATK29INT %1MaxMP100MATK %1Physical Resistance %6Base Stability %60",
        "item_obtainfrom": "[NPC]Blacksmith : ZaldoSofya City: Blacksmith",
        "item_prop": "SellUnknownProcess12 Wood"
    },
    {
        "card_title": "3rd Anniv Staff[Staff]",
        "item_basestat": "Stat/EffectAmountBase ATK29Base Stability %60Potential19",
        "item_obtainfrom": "[Player]Smith Skill-",
        "item_prop": "SellUnknownProcess12 Wood"
    },
    {
        "card_title": "4th Anniv Staff[Staff]",
        "item_basestat": "Stat/EffectAmountBase ATK29INT %1MaxMP100MATK %1Physical Resistance %6Base Stability %60",
        "item_obtainfrom": "[NPC]Blacksmith : ZaldoSofya City: Blacksmith",
        "item_prop": "Sell25 SpinaProcess12 Wood"
    },
    {
        "card_title": "4th Anniv Staff[Staff]",
        "item_basestat": "Stat/EffectAmountBase ATK29Base Stability %60Potential19",
        "item_obtainfrom": "[Player]Smith Skill-",
        "item_prop": "Sell25 SpinaProcess12 Wood"
    },
    {
        "card_title": "Bloom of Peace[Staff]",
        "item_basestat": "Stat/EffectAmountBase ATK32Magic Pierce %10Aggro %-100Light Element1Attack MP Recovery3Base Stability %90",
        "item_obtainfrom": "Granny(Lv 88)Abyss of No Return: Area 3",
        "item_prop": "Sell1 SpinaProcess2 Medicine"
    },
    {
        "card_title": "Water Staff[Staff]",
        "item_basestat": "Stat/EffectAmountBase ATK32DEX2Aggro %-5Water Element1Base Stability %60",
        "item_obtainfrom": "Elizard(Lv 33)Land Of Chaos",
        "item_prop": "Sell30 SpinaProcess15 Wood"
    },
    {
        "card_title": "Water Staff[Staff]",
        "item_basestat": "Stat/EffectAmountBase ATK32DEX3Aggro %-10Water Element1Base Stability %60",
        "item_obtainfrom": "[NPC]Blacksmith : ZaldoSofya City: Blacksmith",
        "item_prop": "Sell30 SpinaProcess15 Wood"
    },
    {
        "card_title": "Water Staff[Staff]",
        "item_basestat": "Stat/EffectAmountBase ATK32Base Stability %60Potential19",
        "item_obtainfrom": "[Player]Smith Skill-",
        "item_prop": "Sell30 SpinaProcess15 Wood"
    },
    {
        "card_title": "Minotaur Staff[Staff]",
        "item_basestat": "Stat/EffectAmountBase ATK34ASPD %-10Fire Element1Attack MP Recovery2Base Stability %55",
        "item_obtainfrom": "Minotaur(Lv 32)Ruined Temple: Forbidden hall",
        "item_prop": "Sell30 SpinaProcess15 Beast"
    },
    {
        "card_title": "Lollipop Staff[Staff]",
        "item_basestat": "Stat/EffectAmountBase ATK35Natural HP Regen %3MaxMP100Light Element1Base Stability %60",
        "item_obtainfrom": "[NPC]Blacksmith : ZaldoSofya City: Blacksmith",
        "item_prop": "SellUnknownProcessN/A"
    },
    {
        "card_title": "Morning Star[Staff]",
        "item_basestat": "Stat/EffectAmountBase ATK44MaxMP300MATK-1200ASPD600Base Stability %60",
        "item_obtainfrom": "Miracle Potum(Lv 42)Ruined Temple: Area 2",
        "item_prop": "Sell1 SpinaProcess2 Metal"
    },
    {
        "card_title": "Rock Staff[Staff]",
        "item_basestat": "Stat/EffectAmountBase ATK44DEF %3Physical Resistance %1Guard Recharge %2Earth Element1Base Stability %60",
        "item_obtainfrom": "Fin Frog(Lv 47)Haotas Ravine",
        "item_prop": "Sell40 SpinaProcess20 Wood"
    },
    {
        "card_title": "Rock Staff[Staff]",
        "item_basestat": "Stat/EffectAmountBase ATK44DEF %5Physical Resistance %1Guard Recharge %3Earth Element1Base Stability %60",
        "item_obtainfrom": "[NPC]Blacksmith : ZaldoSofya City: Blacksmith",
        "item_prop": "Sell40 SpinaProcess20 Wood"
    },
    {
        "card_title": "Rock Staff[Staff]",
        "item_basestat": "Stat/EffectAmountBase ATK44Base Stability %60Potential21",
        "item_obtainfrom": "[Player]Smith Skill-",
        "item_prop": "Sell40 SpinaProcess20 Wood"
    },
    {
        "card_title": "Ooze Staff[Staff]",
        "item_basestat": "Stat/EffectAmountBase ATK49VIT %4MaxHP %8MATK %1Aggro %-16Base Stability %60",
        "item_obtainfrom": "Ooze(Lv 52)Lutaros Cavern: Deepest Part",
        "item_prop": "Sell45 SpinaProcess22 Metal"
    },
    {
        "card_title": "Ooze Staff[Staff]",
        "item_basestat": "Stat/EffectAmountBase ATK49VIT %2MaxHP %12MATK %1Aggro %-8Base Stability %60",
        "item_obtainfrom": "[NPC]Blacksmith : ZaldoSofya City: Blacksmith",
        "item_prop": "Sell45 SpinaProcess22 Metal"
    },
    {
        "card_title": "Ooze Staff[Staff]",
        "item_basestat": "Stat/EffectAmountBase ATK49Base Stability %60Potential22",
        "item_obtainfrom": "[Player]Smith Skill-",
        "item_prop": "Sell45 SpinaProcess22 Metal"
    },
    {
        "card_title": "Ooze Staff[Staff]",
        "item_basestat": "Stat/EffectAmountBase ATK49VIT %6MaxHP %4MATK %2Aggro %-12Base Stability %60",
        "item_obtainfrom": "empty",
        "item_prop": "Sell45 SpinaProcess22 Metal"
    },
    {
        "card_title": "Fire Staff[Staff]",
        "item_basestat": "Stat/EffectAmountBase ATK54Natural MP Regen %-15MATK %2Fire resistance %10Fire Element1Base Stability %60",
        "item_obtainfrom": "[NPC]Blacksmith : ZaldoSofya City: Blacksmith",
        "item_prop": "Sell50 SpinaProcess25 Wood"
    },
    {
        "card_title": "Fire Staff[Staff]",
        "item_basestat": "Stat/EffectAmountBase ATK54Base Stability %60Potential23",
        "item_obtainfrom": "[Player]Smith Skill-",
        "item_prop": "Sell50 SpinaProcess25 Wood"
    },
    {
        "card_title": "Fire Staff[Staff]",
        "item_basestat": "Stat/EffectAmountBase ATK54Natural MP Regen %-5MATK %2Fire resistance %5Fire Element1Base Stability %60",
        "item_obtainfrom": "Abyss Eye(Lv 58)Vyshed the Tainted Land: Area 1",
        "item_prop": "Sell50 SpinaProcess25 Wood"
    },
    {
        "card_title": "1st Anniv Staff II[Staff]",
        "item_basestat": "Stat/EffectAmountBase ATK55INT %2MaxMP200MATK %2Physical Resistance %9Base Stability %60",
        "item_obtainfrom": "[NPC]Blacksmith : ZaldoSofya City: Blacksmith",
        "item_prop": "Sell50 SpinaProcess23 Wood"
    },
    {
        "card_title": "1st Anniv Staff II[Staff]",
        "item_basestat": "Stat/EffectAmountBase ATK55Base Stability %60Potential23",
        "item_obtainfrom": "[Player]Smith Skill-",
        "item_prop": "Sell50 SpinaProcess23 Wood"
    },
    {
        "card_title": "2nd Anniv Staff II[Staff]",
        "item_basestat": "Stat/EffectAmountBase ATK55INT %2MaxMP200MATK %2Physical Resistance %9Base Stability %60",
        "item_obtainfrom": "[NPC]Blacksmith : ZaldoSofya City: Blacksmith",
        "item_prop": "Sell50 SpinaProcess25 Wood"
    },
    {
        "card_title": "2nd Anniv Staff II[Staff]",
        "item_basestat": "Stat/EffectAmountBase ATK55Base Stability %60Potential23",
        "item_obtainfrom": "[Player]Smith Skill-",
        "item_prop": "Sell50 SpinaProcess25 Wood"
    },
    {
        "card_title": "3rd Anniv Staff II[Staff]",
        "item_basestat": "Stat/EffectAmountBase ATK55INT %2MaxMP200MATK %2Physical Resistance %9Base Stability %60",
        "item_obtainfrom": "[NPC]Blacksmith : ZaldoSofya City: Blacksmith",
        "item_prop": "SellUnknownProcess25 Wood"
    },
    {
        "card_title": "3rd Anniv Staff II[Staff]",
        "item_basestat": "Stat/EffectAmountBase ATK55Base Stability %60Potential23",
        "item_obtainfrom": "[Player]Smith Skill-",
        "item_prop": "SellUnknownProcess25 Wood"
    },
    {
        "card_title": "4th Anniv Staff II[Staff]",
        "item_basestat": "Stat/EffectAmountBase ATK55INT %2MaxMP200MATK %2Physical Resistance %9Base Stability %60",
        "item_obtainfrom": "[NPC]Blacksmith : ZaldoSofya City: Blacksmith",
        "item_prop": "Sell50 SpinaProcess25 Wood"
    },
    {
        "card_title": "4th Anniv Staff II[Staff]",
        "item_basestat": "Stat/EffectAmountBase ATK55Base Stability %60Potential23",
        "item_obtainfrom": "[Player]Smith Skill-",
        "item_prop": "Sell50 SpinaProcess25 Wood"
    },
    {
        "card_title": "Abracadabra Cone[Staff]",
        "item_basestat": "Stat/EffectAmountBase ATK55MaxHP500MaxMP300CSPD500Water resistance %5Wind Element1Base Stability %60Guard Break %15",
        "item_obtainfrom": "[NPC]Blacksmith : ZaldoSofya City: Blacksmith",
        "item_prop": "Sell15 SpinaProcessunknown"
    },
    {
        "card_title": "Abracadabra Cone[Staff]",
        "item_basestat": "Stat/EffectAmountBase ATK55Base Stability %60Potential22",
        "item_obtainfrom": "[Player]Smith Skill-",
        "item_prop": "Sell42 SpinaProcessunknown"
    },
    {
        "card_title": "Candy Coryn Staff[Staff]",
        "item_basestat": "Stat/EffectAmountBase ATK62MaxHP777Aggro %-100Water Element1Base Stability %60Physical Barrier777Tumble Unavailable1Magic Barrier777",
        "item_obtainfrom": "[NPC]Lalun (Summer Event Exchange)Event",
        "item_prop": "Sell1 SpinaProcess2 Mana"
    },
    {
        "card_title": "Sakura Staff[Staff]",
        "item_basestat": "Stat/EffectAmountBase ATK67MaxHP %10MaxMP200MATK %1Light Element1Attack MP Recovery1Base Stability %60",
        "item_obtainfrom": "[NPC]Blacksmith : ZaldoSofya City: Blacksmith",
        "item_prop": "Sell60 SpinaProcess30 Wood"
    },
    {
        "card_title": "Sakura Staff[Staff]",
        "item_basestat": "Stat/EffectAmountBase ATK67MaxHP %20MaxMP400MATK %4Light Element1Attack MP Recovery3Weapon ATK300Base Stability %60",
        "item_obtainfrom": "Mimesia (Nightmare)(Lv 180)ABCSakura Castle Donjon: Top",
        "item_prop": "Sell60 SpinaProcess30 Wood"
    },
    {
        "card_title": "Mace of Destruction[Staff]",
        "item_basestat": "Stat/EffectAmountBase ATK70ATK100MATK %2Physical Resistance %4Dark Element1Attack MP Recovery2Base Stability %50",
        "item_obtainfrom": "Boss Roga(Lv 62)Saham Underground Cave - Deepest Part",
        "item_prop": "Sell60 SpinaProcess30 Metal"
    },
    {
        "card_title": "Mace of Destruction[Staff]",
        "item_basestat": "Stat/EffectAmountBase ATK70ATK100MATK %2Physical Resistance %3Dark Element1Attack MP Recovery1Base Stability %50",
        "item_obtainfrom": "[NPC]Blacksmith : ZaldoSofya City: Blacksmith",
        "item_prop": "Sell60 SpinaProcess30 Metal"
    },
    {
        "card_title": "Mace of Destruction[Staff]",
        "item_basestat": "Stat/EffectAmountBase ATK70Base Stability %50Potential24",
        "item_obtainfrom": "[Player]Smith Skill-",
        "item_prop": "Sell60 SpinaProcess30 Metal"
    },
    {
        "card_title": "Storm Staff[Staff]",
        "item_basestat": "Stat/EffectAmountBase ATK70Magic Pierce %6CSPD200Wind resistance %3Wind Element1Base Stability %60",
        "item_obtainfrom": "[NPC]Blacksmith : ZaldoSofya City: Blacksmith",
        "item_prop": "Sell60 SpinaProcess30 Wood"
    },
    {
        "card_title": "Storm Staff[Staff]",
        "item_basestat": "Stat/EffectAmountBase ATK70Base Stability %60Potential24",
        "item_obtainfrom": "[Player]Smith Skill-",
        "item_prop": "Sell60 SpinaProcess30 Wood"
    },
    {
        "card_title": "Storm Staff[Staff]",
        "item_basestat": "Stat/EffectAmountBase ATK72Magic Pierce %4CSPD200Wind resistance %1Wind Element1Base Stability %60",
        "item_obtainfrom": "Sand Anglerfish(Lv 67)Akaku Desert: Area 1",
        "item_prop": "Sell60 SpinaProcess30 Wood"
    },
    {
        "card_title": "Crystal Wand[Staff]",
        "item_basestat": "Stat/EffectAmountBase ATK80CSPD %12Guard Power %3Water Element1Long Range Damage %3Base Stability %60",
        "item_obtainfrom": "Gramp(Lv 79)Abyss of No Return: Area 3",
        "item_prop": "Sell70 SpinaProcess35 Metal"
    },
    {
        "card_title": "Crystal Wand[Staff]",
        "item_basestat": "Stat/EffectAmountBase ATK80CSPD %15Guard Power %5Water Element1Long Range Damage %3Base Stability %60",
        "item_obtainfrom": "[NPC]Blacksmith : ZaldoSofya City: Blacksmith",
        "item_prop": "Sell70 SpinaProcess35 Metal"
    },
    {
        "card_title": "Crystal Wand[Staff]",
        "item_basestat": "Stat/EffectAmountBase ATK80Base Stability %60Potential26",
        "item_obtainfrom": "[Player]Smith Skill-",
        "item_prop": "Sell70 SpinaProcess35 Metal"
    },
    {
        "card_title": "Folium Staff[Staff]",
        "item_basestat": "Stat/EffectAmountBase ATK80INT %3Magic Resistance %10ASPD500Aggro %-3Earth Element1Base Stability %55",
        "item_obtainfrom": "Grass Dragon Yelb(Lv 73)Albatif Village",
        "item_prop": "Sell70 SpinaProcess35 Wood"
    },
    {
        "card_title": "Folium Staff[Staff]",
        "item_basestat": "Stat/EffectAmountBase ATK80INT %3Magic Resistance %5ASPD250Aggro %-9Earth Element1Base Stability %55",
        "item_obtainfrom": "[NPC]Blacksmith : ZaldoSofya City: Blacksmith",
        "item_prop": "Sell70 SpinaProcess35 Wood"
    },
    {
        "card_title": "Folium Staff[Staff]",
        "item_basestat": "Stat/EffectAmountBase ATK80Base Stability %55Potential26",
        "item_obtainfrom": "[Player]Smith Skill-",
        "item_prop": "Sell70 SpinaProcess35 Wood"
    },
    {
        "card_title": "1st Anniv Staff III[Staff]",
        "item_basestat": "Stat/EffectAmountBase ATK87INT %3MaxMP300MATK %3Physical Resistance %12Base Stability %60",
        "item_obtainfrom": "[NPC]Blacksmith : ZaldoSofya City: Blacksmith",
        "item_prop": "Sell75 SpinaProcess37 Wood"
    },
    {
        "card_title": "1st Anniv Staff III[Staff]",
        "item_basestat": "Stat/EffectAmountBase ATK87Base Stability %60Potential27",
        "item_obtainfrom": "[Player]Smith Skill-",
        "item_prop": "Sell75 SpinaProcess37 Wood"
    },
    {
        "card_title": "2nd Anniv Staff III[Staff]",
        "item_basestat": "Stat/EffectAmountBase ATK87INT %3MaxMP300MATK %3Physical Resistance %12Base Stability %60",
        "item_obtainfrom": "[NPC]Blacksmith : ZaldoSofya City: Blacksmith",
        "item_prop": "Sell75 SpinaProcess37 Wood"
    },
    {
        "card_title": "2nd Anniv Staff III[Staff]",
        "item_basestat": "Stat/EffectAmountBase ATK87Base Stability %60Potential27",
        "item_obtainfrom": "[Player]Smith Skill-",
        "item_prop": "Sell75 SpinaProcess37 Wood"
    },
    {
        "card_title": "3rd Anniv Staff III[Staff]",
        "item_basestat": "Stat/EffectAmountBase ATK87INT %3MaxMP300MATK %3Physical Resistance %12Base Stability %60",
        "item_obtainfrom": "[NPC]Blacksmith : ZaldoSofya City: Blacksmith",
        "item_prop": "SellUnknownProcess37 Wood"
    },
    {
        "card_title": "3rd Anniv Staff III[Staff]",
        "item_basestat": "Stat/EffectAmountBase ATK87Base Stability %60Potential27",
        "item_obtainfrom": "[Player]Smith Skill-",
        "item_prop": "SellUnknownProcess37 Wood"
    },
    {
        "card_title": "4th Anniv Staff III[Staff]",
        "item_basestat": "Stat/EffectAmountBase ATK87INT %3MaxMP300MATK %3Physical Resistance %12Base Stability %60",
        "item_obtainfrom": "[NPC]Blacksmith : ZaldoSofya City: Blacksmith",
        "item_prop": "Sell75 SpinaProcess37 Wood"
    },
    {
        "card_title": "4th Anniv Staff III[Staff]",
        "item_basestat": "Stat/EffectAmountBase ATK87Base Stability %60Potential27",
        "item_obtainfrom": "[Player]Smith Skill-",
        "item_prop": "Sell75 SpinaProcess37 Wood"
    },
    {
        "card_title": "5th Anniv Staff[Staff]",
        "item_basestat": "Stat/EffectAmountBase ATK87INT %4MaxMP400MATK %4Physical Resistance %30CSPD %20Base Stability %60",
        "item_obtainfrom": "[NPC]Blacksmith : ZaldoSofya City: Blacksmith",
        "item_prop": "Sell75 SpinaProcess37 Wood"
    },
    {
        "card_title": "5th Anniv Staff[Staff]",
        "item_basestat": "Stat/EffectAmountBase ATK87Base Stability %60Potential27",
        "item_obtainfrom": "[Player]Smith Skill-",
        "item_prop": "Sell75 SpinaProcess37 Wood"
    },
    {
        "card_title": "Devil's Staff[Staff]",
        "item_basestat": "Stat/EffectAmountBase ATK92Base Stability %60Potential28",
        "item_obtainfrom": "[Player]Smith Skill-",
        "item_prop": "SellUnknownProcessunknown"
    },
    {
        "card_title": "Devil's Staff[Staff]",
        "item_basestat": "Stat/EffectAmountBase ATK92MaxHP-300MATK %3Magic Resistance %6Dark Element1Base Stability %60",
        "item_obtainfrom": "[NPC]Blacksmith : ZaldoSofya City: Blacksmith",
        "item_prop": "SellUnknownProcessunknown"
    },
    {
        "card_title": "Devil's Staff[Staff]",
        "item_basestat": "Stat/EffectAmountBase ATK92MaxHP-100MATK %3Magic Resistance %3Dark Element1Base Stability %60",
        "item_obtainfrom": "Aramia(Lv 87)Garden of Sublimation: Area 2",
        "item_prop": "Sell80 SpinaProcess40 Beast"
    },
    {
        "card_title": "Scrader Mace[Staff]",
        "item_basestat": "Stat/EffectAmountBase ATK94Natural MP Regen %-10ATK140Physical Resistance %-20CSPD400Critical Rate5Earth Element1Base Stability %50",
        "item_obtainfrom": "Scrader(Lv 85)Magic Waste Site: Deepest Part",
        "item_prop": "Sell80 SpinaProcess40 Metal"
    },
    {
        "card_title": "Scrader Mace[Staff]",
        "item_basestat": "Stat/EffectAmountBase ATK94Natural HP Regen %-5ATK140Physical Resistance %-10CSPD300Critical Rate5Earth Element1Base Stability %50",
        "item_obtainfrom": "[NPC]Blacksmith : ZaldoSofya City: Blacksmith",
        "item_prop": "Sell80 SpinaProcess40 Metal"
    },
    {
        "card_title": "Scrader Mace[Staff]",
        "item_basestat": "Stat/EffectAmountBase ATK94Base Stability %50Potential28",
        "item_obtainfrom": "[Player]Smith Skill-",
        "item_prop": "Sell80 SpinaProcess40 Metal"
    },
    {
        "card_title": "Jibril's Diary I[Staff]",
        "item_basestat": "Stat/EffectAmountBase ATK100MaxMP300MATK %5Magic Pierce %20Evasion Recharge %10Aggro %-50Dark Element1% stronger against Neutral20Base Stability %60Stun Unavailable1Absolute Dodge %10Reduce Dmg (Straight Line) %10",
        "item_obtainfrom": "empty",
        "item_prop": "Sell80 SpinaProcess1000 Mana"
    },
    {
        "card_title": "6th Anniv Staff[Staff]",
        "item_basestat": "Stat/EffectAmountBase ATK101INT %4MaxMP500MATK %4Physical Resistance %30CSPD %10Base Stability %60Knuckle only:Absolute Dodge %10",
        "item_obtainfrom": "[NPC]Blacksmith : ZaldoSofya City: Blacksmith",
        "item_prop": "Sell85 SpinaProcess42 Wood"
    },
    {
        "card_title": "6th Anniv Staff[Staff]",
        "item_basestat": "Stat/EffectAmountBase ATK101Base Stability %60Potential28",
        "item_obtainfrom": "[Player]Smith Skill-",
        "item_prop": "Sell85 SpinaProcess42 Wood"
    },
    {
        "card_title": "Icestaff Frigus[Staff]",
        "item_basestat": "Stat/EffectAmountBase ATK101Accuracy30Water Element1Short Range Damage %1Base Stability %60Magic Barrier500Additional Magic %150ATK DOWN (STR %)300",
        "item_obtainfrom": "[NPC]Blacksmith : ZaldoSofya City: Blacksmith",
        "item_prop": "Sell85 SpinaProcess42 Mana"
    },
    {
        "card_title": "Icestaff Frigus[Staff]",
        "item_basestat": "Stat/EffectAmountBase ATK101Base Stability %60Potential28",
        "item_obtainfrom": "[Player]Smith Skill-",
        "item_prop": "Sell85 SpinaProcess42 Mana"
    },
    {
        "card_title": "Sage Staff[Staff]",
        "item_basestat": "Stat/EffectAmountBase ATK109MaxMP200MATK %4Magic Pierce %5Fire Element1Base Stability %60",
        "item_obtainfrom": "[NPC]Blacksmith : ZaldoSofya City: Blacksmith",
        "item_prop": "Sell90 SpinaProcess45 Metal"
    },
    {
        "card_title": "Sage Staff[Staff]",
        "item_basestat": "Stat/EffectAmountBase ATK109Base Stability %60Potential29",
        "item_obtainfrom": "[Player]Smith Skill-",
        "item_prop": "Sell90 SpinaProcess45 Metal"
    },
    {
        "card_title": "Sage Staff[Staff]",
        "item_basestat": "Stat/EffectAmountBase ATK109MaxMP100MATK %4Magic Pierce %5Fire Element1Base Stability %60",
        "item_obtainfrom": "Bestion(Lv 98)Blazing Graben: Surface",
        "item_prop": "Sell90 SpinaProcess45 Metal"
    },
    {
        "card_title": "Sweet Spoon[Staff]",
        "item_basestat": "Stat/EffectAmountBase ATK110ASPD-1% stronger against Neutral25Base Stability %60Physical Barrier1000",
        "item_obtainfrom": "[NPC]Blacksmith : ZaldoSofya City: Blacksmith",
        "item_prop": "Sell1 SpinaProcess100 Mana"
    },
    {
        "card_title": "2nd Anniv Staff IV[Staff]",
        "item_basestat": "Stat/EffectAmountBase ATK117INT %4MaxMP400MATK %4Physical Resistance %15Base Stability %60",
        "item_obtainfrom": "[NPC]Blacksmith : ZaldoSofya City: Blacksmith",
        "item_prop": "Sell95 SpinaProcess47 Wood"
    },
    {
        "card_title": "2nd Anniv Staff IV[Staff]",
        "item_basestat": "Stat/EffectAmountBase ATK117Base Stability %60Potential30",
        "item_obtainfrom": "[Player]Smith Skill-",
        "item_prop": "Sell95 SpinaProcess47 Wood"
    },
    {
        "card_title": "3rd Anniv Staff IV[Staff]",
        "item_basestat": "Stat/EffectAmountBase ATK117INT %4MaxMP400MATK %4Physical Resistance %15Base Stability %60",
        "item_obtainfrom": "[NPC]Blacksmith : ZaldoSofya City: Blacksmith",
        "item_prop": "SellUnknownProcess47 Wood"
    },
    {
        "card_title": "3rd Anniv Staff IV[Staff]",
        "item_basestat": "Stat/EffectAmountBase ATK117Base Stability %60Potential30",
        "item_obtainfrom": "[Player]Smith Skill-",
        "item_prop": "SellUnknownProcess47 Wood"
    },
    {
        "card_title": "4th Anniv Staff IV[Staff]",
        "item_basestat": "Stat/EffectAmountBase ATK117INT %4MaxMP400MATK %4Physical Resistance %15Base Stability %60",
        "item_obtainfrom": "[NPC]Blacksmith : ZaldoSofya City: Blacksmith",
        "item_prop": "Sell95 SpinaProcess47 Wood"
    },
    {
        "card_title": "4th Anniv Staff IV[Staff]",
        "item_basestat": "Stat/EffectAmountBase ATK117Base Stability %60Potential30",
        "item_obtainfrom": "[Player]Smith Skill-",
        "item_prop": "Sell95 SpinaProcess47 Wood"
    },
    {
        "card_title": "Bexiz Staff[Staff]",
        "item_basestat": "Stat/EffectAmountBase ATK125AGI %12Dodge6CSPD500Evasion Recharge %10% stronger against Neutral25Base Stability %60",
        "item_obtainfrom": "Bexiz(Lv 103)Cradle of Soldier: Deepest Part",
        "item_prop": "Sell100 SpinaProcess50 Metal"
    },
    {
        "card_title": "Bexiz Staff[Staff]",
        "item_basestat": "Stat/EffectAmountBase ATK125AGI %6Dodge3CSPD500Evasion Recharge %5% stronger against Neutral25Base Stability %60",
        "item_obtainfrom": "[NPC]Blacksmith : ZaldoSofya City: Blacksmith",
        "item_prop": "Sell100 SpinaProcess50 Metal"
    },
    {
        "card_title": "Bexiz Staff[Staff]",
        "item_basestat": "Stat/EffectAmountBase ATK125Base Stability %60Potential31",
        "item_obtainfrom": "[Player]Smith Skill-",
        "item_prop": "Sell100 SpinaProcess50 Metal"
    },
    {
        "card_title": "Bexiz Staff[Staff]",
        "item_basestat": "Stat/EffectAmountBase ATK125AGI %1Dodge1CSPD1000Evasion Recharge %1% stronger against Neutral25Base Stability %60",
        "item_obtainfrom": "Bexiz (Megiston 2017)(Lv 140)Event",
        "item_prop": "Sell100 SpinaProcess50 Metal"
    },
    {
        "card_title": "HATSUNE MIKU Microphone Stick[Staff]",
        "item_basestat": "Stat/EffectAmountBase ATK125MaxMP300MATK %4Physical Resistance %30Magic Resistance %30CSPD1000Ailment Resistance %15Light Element1Base Stability %70",
        "item_obtainfrom": "[Orb Shop]Avatar ChestsOrb Shop",
        "item_prop": "SellUnknownProcessunknown"
    },
    {
        "card_title": "Priest Mace[Staff]",
        "item_basestat": "Stat/EffectAmountBase ATK130Accuracy30ASPD1000Critical Rate15Light Element1Base Stability %60",
        "item_obtainfrom": "[NPC]Blacksmith : ZaldoSofya City: Blacksmith",
        "item_prop": "Sell100 SpinaProcess50 Metal"
    },
    {
        "card_title": "Priest Mace[Staff]",
        "item_basestat": "Stat/EffectAmountBase ATK130Base Stability %60Potential31",
        "item_obtainfrom": "[Player]Smith Skill-",
        "item_prop": "Sell100 SpinaProcess50 Metal"
    },
    {
        "card_title": "Priest Mace[Staff]",
        "item_basestat": "Stat/EffectAmountBase ATK130Accuracy30ASPD750Critical Rate15Light Element1Base Stability %60",
        "item_obtainfrom": "Horn Machina(Lv 110)Large Demi Machina Factory: Area 1",
        "item_prop": "Sell100 SpinaProcess50 Metal"
    },
    {
        "card_title": "Vulcan Staff[Staff]",
        "item_basestat": "Stat/EffectAmountBase ATK140MaxHP1000Magic Resistance %12% stronger against Earth8Fire resistance %6Fire Element1Base Stability %60",
        "item_obtainfrom": "Ifrid(Lv 112)Blazing Graben: Deepest Part",
        "item_prop": "Sell110 SpinaProcess55 Mana"
    },
    {
        "card_title": "Vulcan Staff[Staff]",
        "item_basestat": "Stat/EffectAmountBase ATK140MaxHP1000Magic Resistance %24% stronger against Earth4Fire resistance %12Fire Element1Base Stability %60",
        "item_obtainfrom": "[NPC]Blacksmith : ZaldoSofya City: Blacksmith",
        "item_prop": "Sell110 SpinaProcess55 Mana"
    },
    {
        "card_title": "Vulcan Staff[Staff]",
        "item_basestat": "Stat/EffectAmountBase ATK140Base Stability %60Potential32",
        "item_obtainfrom": "[Player]Smith Skill-",
        "item_prop": "Sell110 SpinaProcess55 Mana"
    },
    {
        "card_title": "2nd Anniv Staff V[Staff]",
        "item_basestat": "Stat/EffectAmountBase ATK142INT %5MaxMP500MATK %5Physical Resistance %18Base Stability %60",
        "item_obtainfrom": "[NPC]Blacksmith : ZaldoSofya City: Blacksmith",
        "item_prop": "Sell110 SpinaProcess55 Wood"
    },
    {
        "card_title": "2nd Anniv Staff V[Staff]",
        "item_basestat": "Stat/EffectAmountBase ATK142Base Stability %60Potential32",
        "item_obtainfrom": "[Player]Smith Skill-",
        "item_prop": "Sell110 SpinaProcess55 Wood"
    },
    {
        "card_title": "3rd Anniv Staff V[Staff]",
        "item_basestat": "Stat/EffectAmountBase ATK142INT %5MaxMP500MATK %5Physical Resistance %18Base Stability %60",
        "item_obtainfrom": "[NPC]Blacksmith : ZaldoSofya City: Blacksmith",
        "item_prop": "SellUnknownProcess55 Wood"
    },
    {
        "card_title": "3rd Anniv Staff V[Staff]",
        "item_basestat": "Stat/EffectAmountBase ATK142Base Stability %60Potential32",
        "item_obtainfrom": "[Player]Smith Skill-",
        "item_prop": "SellUnknownProcess55 Wood"
    },
    {
        "card_title": "4th Anniv Staff V[Staff]",
        "item_basestat": "Stat/EffectAmountBase ATK142INT %5MaxMP500MATK %5Physical Resistance %18Base Stability %60",
        "item_obtainfrom": "[NPC]Blacksmith : ZaldoSofya City: Blacksmith",
        "item_prop": "Sell110 SpinaProcess55 Wood"
    },
    {
        "card_title": "4th Anniv Staff V[Staff]",
        "item_basestat": "Stat/EffectAmountBase ATK142Base Stability %60Potential32",
        "item_obtainfrom": "[Player]Smith Skill-",
        "item_prop": "Sell110 SpinaProcess55 Wood"
    },
    {
        "card_title": "5th Anniv Staff II[Staff]",
        "item_basestat": "Stat/EffectAmountBase ATK142INT %5MaxMP450MATK %5Physical Resistance %30CSPD %25Base Stability %60",
        "item_obtainfrom": "[NPC]Blacksmith : ZaldoSofya City: Blacksmith",
        "item_prop": "Sell110 SpinaProcess55 Wood"
    },
    {
        "card_title": "5th Anniv Staff II[Staff]",
        "item_basestat": "Stat/EffectAmountBase ATK142Base Stability %60Potential32",
        "item_obtainfrom": "[Player]Smith Skill-",
        "item_prop": "Sell110 SpinaProcess55 Wood"
    },
    {
        "card_title": "Abracadabra Cone II[Staff]",
        "item_basestat": "Stat/EffectAmountBase ATK142MaxHP1000MaxMP300CSPD750Water resistance %10Wind Element1Base Stability %60Guard Break %20",
        "item_obtainfrom": "[NPC]Blacksmith : ZaldoSofya City: Blacksmith",
        "item_prop": "Sell16 SpinaProcessunknown"
    },
    {
        "card_title": "Abracadabra Cone II[Staff]",
        "item_basestat": "Stat/EffectAmountBase ATK142Base Stability %60Potential31",
        "item_obtainfrom": "[Player]Smith Skill-",
        "item_prop": "Sell43 SpinaProcessunknown"
    },
    {
        "card_title": "Crystal Rod[Staff]",
        "item_basestat": "Stat/EffectAmountBase ATK142MATK %4Magic Pierce %30Base Stability %60Guard Break %15",
        "item_obtainfrom": "[NPC]Blacksmith : ZaldoSofya City: Blacksmith",
        "item_prop": "Sell110 SpinaProcess55 Metal"
    },
    {
        "card_title": "Crystal Rod[Staff]",
        "item_basestat": "Stat/EffectAmountBase ATK142Base Stability %60Potential32",
        "item_obtainfrom": "[Player]Smith Skill-",
        "item_prop": "Sell110 SpinaProcess55 Metal"
    },
    {
        "card_title": "Crystal Rod[Staff]",
        "item_basestat": "Stat/EffectAmountBase ATK142MATK %4Magic Pierce %25Base Stability %60Guard Break %20",
        "item_obtainfrom": "Singing Eye(Lv 108)Ultimea Sewer: Southeast",
        "item_prop": "Sell110 SpinaProcess55 Metal"
    },
    {
        "card_title": "HATSUNE MIKU's Handbell[Staff]",
        "item_basestat": "Stat/EffectAmountBase ATK150MaxHP3000MaxMP300MATK %4Magic Pierce %20CSPD500Critical Rate25Water Element1Base Stability %70",
        "item_obtainfrom": "[Orb Shop]Avatar ChestsOrb Shop",
        "item_prop": "SellUnknownProcessunknown"
    },
    {
        "card_title": "Red Steel Staff[Staff]",
        "item_basestat": "Stat/EffectAmountBase ATK150MaxHP %50Critical Rate100Fire Element1Base Stability %80",
        "item_obtainfrom": "Red Steel Box-",
        "item_prop": "SellUnknownProcessunknown"
    },
    {
        "card_title": "6th Anniv Staff II[Staff]",
        "item_basestat": "Stat/EffectAmountBase ATK160INT %5MaxMP500MATK %5Physical Resistance %30CSPD %20Base Stability %60Knuckle only:Absolute Dodge %10",
        "item_obtainfrom": "[NPC]Blacksmith : ZaldoSofya City: Blacksmith",
        "item_prop": "Sell120 SpinaProcess60 Wood"
    },
    {
        "card_title": "6th Anniv Staff II[Staff]",
        "item_basestat": "Stat/EffectAmountBase ATK160Base Stability %60Potential34",
        "item_obtainfrom": "[Player]Smith Skill-",
        "item_prop": "Sell120 SpinaProcess60 Wood"
    },
    {
        "card_title": "7th Anniv Staff[Staff]",
        "item_basestat": "Stat/EffectAmountBase ATK160INT %4MATK %4Magic Pierce %10CSPD %40Critical Rate30Base Stability %60Reduce Dmg (Bullet) %30Attack Range (m)2",
        "item_obtainfrom": "[NPC]Blacksmith : ZaldoSofya City: Blacksmith",
        "item_prop": "Sell120 SpinaProcess60 Wood"
    },
    {
        "card_title": "7th Anniv Staff[Staff]",
        "item_basestat": "Stat/EffectAmountBase ATK160Base Stability %60Potential34Attack Range (m)2",
        "item_obtainfrom": "[Player]Smith Skill-",
        "item_prop": "Sell120 SpinaProcess60 Wood"
    },
    {
        "card_title": "Dia Staff[Staff]",
        "item_basestat": "Stat/EffectAmountBase ATK160INT %4MaxMP300MATK %4Dark resistance %10Aggro %-50Light Element1Base Stability %60",
        "item_obtainfrom": "[NPC]Blacksmith : ZaldoSofya City: Blacksmith",
        "item_prop": "Sell120 SpinaProcess60 Wood"
    },
    {
        "card_title": "Fleur Rod[Staff]",
        "item_basestat": "Stat/EffectAmountBase ATK161MATK %5Earth Element1Base Stability %70Fractional Barrier %15Reduce Dmg (Charge) %10",
        "item_obtainfrom": "Fanalizard(Lv 132)Curonne Forest: North Area 1",
        "item_prop": "Sell130 SpinaProcess65 Metal"
    },
    {
        "card_title": "Fleur Rod[Staff]",
        "item_basestat": "Stat/EffectAmountBase ATK161MATK %5Earth Element1Base Stability %70Fractional Barrier %10Reduce Dmg (Charge) %20",
        "item_obtainfrom": "[NPC]Blacksmith : ZaldoSofya City: Blacksmith",
        "item_prop": "Sell130 SpinaProcess65 Metal"
    },
    {
        "card_title": "Fleur Rod[Staff]",
        "item_basestat": "Stat/EffectAmountBase ATK161Base Stability %70Potential36",
        "item_obtainfrom": "[Player]Smith Skill-",
        "item_prop": "Sell130 SpinaProcess65 Metal"
    },
    {
        "card_title": "Sunflower[Staff]",
        "item_basestat": "Stat/EffectAmountBase ATK170Aggro %-40Light Element1Base Stability %70Fractional Barrier %20Reduce Dmg (Charge) %-100Reduce Dmg (Bullet) %20Reduce Dmg (Bowling) %20",
        "item_obtainfrom": "empty",
        "item_prop": "Sell1 SpinaProcess2 Medicine"
    },
    {
        "card_title": "3rd Anniv Staff VI[Staff]",
        "item_basestat": "Stat/EffectAmountBase ATK179INT %6MaxMP500MATK %6Physical Resistance %21CSPD %10Base Stability %60",
        "item_obtainfrom": "[NPC]Blacksmith : ZaldoSofya City: Blacksmith",
        "item_prop": "SellUnknownProcess65 Wood"
    },
    {
        "card_title": "3rd Anniv Staff VI[Staff]",
        "item_basestat": "Stat/EffectAmountBase ATK179Base Stability %60Potential36",
        "item_obtainfrom": "[Player]Smith Skill-",
        "item_prop": "SellUnknownProcess65 Wood"
    },
    {
        "card_title": "4th Anniv Staff VI[Staff]",
        "item_basestat": "Stat/EffectAmountBase ATK179INT %6MaxMP500MATK %6Physical Resistance %21CSPD %10Base Stability %60",
        "item_obtainfrom": "[NPC]Blacksmith : ZaldoSofya City: Blacksmith",
        "item_prop": "Sell130 SpinaProcess65 Wood"
    },
    {
        "card_title": "4th Anniv Staff VI[Staff]",
        "item_basestat": "Stat/EffectAmountBase ATK179Base Stability %60Potential36",
        "item_obtainfrom": "[Player]Smith Skill-",
        "item_prop": "Sell130 SpinaProcess65 Wood"
    },
    {
        "card_title": "Elegia Staff[Staff]",
        "item_basestat": "Stat/EffectAmountBase ATK180MaxMP300MATK %4Dark Element1Base Stability %60Reduce Dmg (Meteor) %15",
        "item_obtainfrom": "Lyark Defender(Lv 127)Ultimea Palace: Storage Area 1",
        "item_prop": "Sell120 SpinaProcess60 Metal"
    },
    {
        "card_title": "Elegia Staff[Staff]",
        "item_basestat": "Stat/EffectAmountBase ATK180MaxMP400MATK %4Dark Element1Base Stability %60Reduce Dmg (Meteor) %20",
        "item_obtainfrom": "[NPC]Blacksmith : ZaldoSofya City: Blacksmith",
        "item_prop": "Sell120 SpinaProcess60 Metal"
    },
    {
        "card_title": "Elegia Staff[Staff]",
        "item_basestat": "Stat/EffectAmountBase ATK180Base Stability %60Potential34",
        "item_obtainfrom": "[Player]Smith Skill-",
        "item_prop": "Sell130 SpinaProcess65 Metal"
    },
    {
        "card_title": "Spirit's Tear[Staff]",
        "item_basestat": "Stat/EffectAmountBase ATK180ATK %-100ASPD-1000Water Element1Attack MP Recovery80Base Stability %60MATK UP (VIT %)100MATK DOWN (DEX %)100",
        "item_obtainfrom": "Lalvada(Lv 117)Monster's Forest: Deep Part",
        "item_prop": "Sell130 SpinaProcess65 Wood"
    },
    {
        "card_title": "Spirit's Tear[Staff]",
        "item_basestat": "Stat/EffectAmountBase ATK180ATK %-100ASPD-500Water Element1Attack MP Recovery40Base Stability %60MATK UP (VIT %)100MATK DOWN (DEX %)100",
        "item_obtainfrom": "[NPC]Blacksmith : ZaldoSofya City: Blacksmith",
        "item_prop": "Sell130 SpinaProcess65 Wood"
    },
    {
        "card_title": "Spirit's Tear[Staff]",
        "item_basestat": "Stat/EffectAmountBase ATK180Base Stability %60Potential36",
        "item_obtainfrom": "[Player]Smith Skill-",
        "item_prop": "Sell130 SpinaProcess65 Wood"
    },
    {
        "card_title": "Laurel Staff[Staff]",
        "item_basestat": "Stat/EffectAmountBase ATK199CSPD750Wind Element1Base Stability %60Anticipate %15",
        "item_obtainfrom": "Destiny Cube(Lv 144)Shrine of The Gods: Area 2",
        "item_prop": "Sell140 SpinaProcess70 Metal"
    },
    {
        "card_title": "Laurel Staff[Staff]",
        "item_basestat": "Stat/EffectAmountBase ATK199CSPD1000Wind Element1Base Stability %60Anticipate %10",
        "item_obtainfrom": "[NPC]Blacksmith : ZaldoSofya City: Blacksmith",
        "item_prop": "Sell140 SpinaProcess70 Metal"
    },
    {
        "card_title": "Laurel Staff[Staff]",
        "item_basestat": "Stat/EffectAmountBase ATK199Base Stability %60Potential37",
        "item_obtainfrom": "[Player]Smith Skill-",
        "item_prop": "Sell140 SpinaProcess70 Metal"
    },
    {
        "card_title": "Golden Rod[Staff]",
        "item_basestat": "Stat/EffectAmountBase ATK206MaxMP300MATK %6DEF %20Base Stability %60Physical Barrier1000Additional Magic %100",
        "item_obtainfrom": "Felicitoad(Lv 140)Sofya City: Government Office",
        "item_prop": "SellUnknownProcessunknown"
    },
    {
        "card_title": "3rd Anniv Staff VII[Staff]",
        "item_basestat": "Stat/EffectAmountBase ATK209INT %6MaxMP500MATK %6Physical Resistance %24CSPD %20Base Stability %60",
        "item_obtainfrom": "[NPC]Blacksmith : ZaldoSofya City: Blacksmith",
        "item_prop": "SellUnknownProcess72 Wood"
    },
    {
        "card_title": "3rd Anniv Staff VII[Staff]",
        "item_basestat": "Stat/EffectAmountBase ATK209Base Stability %60Potential38",
        "item_obtainfrom": "[Player]Smith Skill-",
        "item_prop": "SellUnknownProcess72 Wood"
    },
    {
        "card_title": "4th Anniv Staff VII[Staff]",
        "item_basestat": "Stat/EffectAmountBase ATK209INT %6MaxMP500MATK %6Physical Resistance %24CSPD %20Base Stability %60",
        "item_obtainfrom": "[NPC]Blacksmith : ZaldoSofya City: Blacksmith",
        "item_prop": "Sell145 SpinaProcess72 Wood"
    },
    {
        "card_title": "4th Anniv Staff VII[Staff]",
        "item_basestat": "Stat/EffectAmountBase ATK209Base Stability %60Potential38",
        "item_obtainfrom": "[Player]Smith Skill-",
        "item_prop": "Sell145 SpinaProcess72 Wood"
    },
    {
        "card_title": "5th Anniv Staff III[Staff]",
        "item_basestat": "Stat/EffectAmountBase ATK209INT %6MaxMP500MATK %6Physical Resistance %30CSPD %30Base Stability %60",
        "item_obtainfrom": "[NPC]Blacksmith : ZaldoSofya City: Blacksmith",
        "item_prop": "Sell145 SpinaProcess72 Wood"
    },
    {
        "card_title": "5th Anniv Staff III[Staff]",
        "item_basestat": "Stat/EffectAmountBase ATK209Base Stability %60Potential38",
        "item_obtainfrom": "[Player]Smith Skill-",
        "item_prop": "Sell145 SpinaProcess72 Wood"
    },
    {
        "card_title": "Mischievous Magic Book[Staff]",
        "item_basestat": "Stat/EffectAmountBase ATK210MaxHP3000MaxMP300% stronger against Neutral25Base Stability %70",
        "item_obtainfrom": "[NPC]Blacksmith : ZaldoSofya City: Blacksmith",
        "item_prop": "SellUnknownProcessunknown"
    },
    {
        "card_title": "6th Anniv Staff III[Staff]",
        "item_basestat": "Stat/EffectAmountBase ATK220INT %6MaxMP600MATK %6Physical Resistance %30CSPD %30Base Stability %60Reduce Dmg (Bullet) %2Knuckle only:Absolute Dodge %10",
        "item_obtainfrom": "[NPC]Blacksmith : ZaldoSofya City: Blacksmith",
        "item_prop": "Sell150 SpinaProcess75 Wood"
    },
    {
        "card_title": "6th Anniv Staff III[Staff]",
        "item_basestat": "Stat/EffectAmountBase ATK220Base Stability %60Potential39",
        "item_obtainfrom": "[Player]Smith Skill-",
        "item_prop": "Sell150 SpinaProcess75 Wood"
    },
    {
        "card_title": "7th Anniv Staff II[Staff]",
        "item_basestat": "Stat/EffectAmountBase ATK220INT %6MATK %6Magic Pierce %12CSPD %48Critical Rate30Base Stability %60Reduce Dmg (Bullet) %30Attack Range (m)2",
        "item_obtainfrom": "[NPC]Blacksmith : ZaldoSofya City: Blacksmith",
        "item_prop": "Sell150 SpinaProcess75 Wood"
    },
    {
        "card_title": "7th Anniv Staff II[Staff]",
        "item_basestat": "Stat/EffectAmountBase ATK220Base Stability %60Potential39Attack Range (m)2",
        "item_obtainfrom": "[Player]Smith Skill-",
        "item_prop": "Sell150 SpinaProcess75 Wood"
    },
    {
        "card_title": "8th Anniv Staff[Staff]",
        "item_basestat": "Stat/EffectAmountBase ATK220INT %6MATK %6Magic Pierce %15Critical Rate35Critical Rate %50Base Stability %60Reduce Dmg (Bullet) %35Attack Range (m)2",
        "item_obtainfrom": "[NPC]Blacksmith : ZaldoSofya City: Blacksmith",
        "item_prop": "Sell150 SpinaProcess75 Wood"
    },
    {
        "card_title": "8th Anniv Staff[Staff]",
        "item_basestat": "Stat/EffectAmountBase ATK220Base Stability %60Potential39Attack Range (m)2",
        "item_obtainfrom": "[Player]Smith Skill-",
        "item_prop": "Sell150 SpinaProcess75 Wood"
    },
    {
        "card_title": "Luminous Mushroom Staff[Staff]",
        "item_basestat": "Stat/EffectAmountBase ATK220MaxHP3000MATK %6Aggro %-20Light Element1Base Stability %60Reduce Dmg (Bullet) %15",
        "item_obtainfrom": "Shampy(Lv 135)Turnus Mine: Hall",
        "item_prop": "Sell150 SpinaProcess75 Wood"
    },
    {
        "card_title": "Luminous Mushroom Staff[Staff]",
        "item_basestat": "Stat/EffectAmountBase ATK220MaxHP1500MATK %6Aggro %-20Light Element1Base Stability %60Reduce Dmg (Bullet) %30",
        "item_obtainfrom": "[NPC]Blacksmith : ZaldoSofya City: Blacksmith",
        "item_prop": "Sell150 SpinaProcess75 Wood"
    },
    {
        "card_title": "Luminous Mushroom Staff[Staff]",
        "item_basestat": "Stat/EffectAmountBase ATK220Base Stability %60Potential39",
        "item_obtainfrom": "[Player]Smith Skill-",
        "item_prop": "Sell150 SpinaProcess75 Wood"
    },
    {
        "card_title": "Queen Staff (Potum)[Staff]",
        "item_basestat": "Stat/EffectAmountBase ATK220MaxMP1000MATK %10CSPD-9999Base Stability %60MATK UP (INT %)100MATK DOWN (VIT %)100",
        "item_obtainfrom": "Platinum Potum (Normal) (6M DL)(Lv 100)Event",
        "item_prop": "Sell1 SpinaProcess1000 Mana"
    },
    {
        "card_title": "Sakura Lantern Staff[Staff]",
        "item_basestat": "Stat/EffectAmountBase ATK220MaxMP500MATK %6% stronger against Earth25Ailment Resistance %5Aggro %-20Earth Element1Base Stability %60",
        "item_obtainfrom": "[NPC]Blacksmith : ZaldoSofya City: Blacksmith",
        "item_prop": "Sell150 SpinaProcess75 Wood"
    },
    {
        "card_title": "Lil Empress Staff[Staff]",
        "item_basestat": "Stat/EffectAmountBase ATK229MATK %6CSPD200Critical Rate25Aggro %-15Fire Element1Base Stability %55",
        "item_obtainfrom": "Venena Coenubia (YK Wifey)(Lv 140)Ultimea Palace: Throne",
        "item_prop": "Sell145 SpinaProcess72 Mana"
    },
    {
        "card_title": "Lil Empress Staff[Staff]",
        "item_basestat": "Stat/EffectAmountBase ATK229MATK %6CSPD600Critical Rate20Aggro %-10Fire Element1Base Stability %55",
        "item_obtainfrom": "[NPC]Blacksmith : ZaldoSofya City: Blacksmith",
        "item_prop": "Sell145 SpinaProcess72 Mana"
    },
    {
        "card_title": "Lil Empress Staff[Staff]",
        "item_basestat": "Stat/EffectAmountBase ATK229Base Stability %55Potential38",
        "item_obtainfrom": "[Player]Smith Skill-",
        "item_prop": "Sell145 SpinaProcess72 Mana"
    },
    {
        "card_title": "Sacred Ice Staff[Staff]",
        "item_basestat": "Stat/EffectAmountBase ATK231MaxMP300MATK %6% stronger against Light-25% stronger against Dark10Ailment Resistance %5Water Element1Base Stability %65MATK UP (STR %)100",
        "item_obtainfrom": "Noeliel the Ice Statue(Lv 141)Noeliel Castle: Hall (120-140)",
        "item_prop": "SellUnknownProcessunknown"
    },
    {
        "card_title": "Sacred Ice Staff[Staff]",
        "item_basestat": "Stat/EffectAmountBase ATK231MaxMP100MATK %2% stronger against Light-25% stronger against Dark10Ailment Resistance %1Water Element1Base Stability %65MATK UP (STR %)100",
        "item_obtainfrom": "Noeliel the Ice Statue(Lv 102)Noeliel Castle: Hall (80-100)",
        "item_prop": "SellUnknownProcessunknown"
    },
    {
        "card_title": "Sacred Ice Staff[Staff]",
        "item_basestat": "Stat/EffectAmountBase ATK231MaxMP200MATK %4% stronger against Light-25% stronger against Dark10Ailment Resistance %3Water Element1Base Stability %65MATK UP (STR %)100",
        "item_obtainfrom": "Noeliel the Ice Statue(Lv 122)Noeliel Castle: Hall (100-120)",
        "item_prop": "SellUnknownProcessunknown"
    },
    {
        "card_title": "4th Anniv Staff VIII[Staff]",
        "item_basestat": "Stat/EffectAmountBase ATK242INT %6MaxMP500MATK %6Physical Resistance %27CSPD %30Base Stability %60",
        "item_obtainfrom": "[NPC]Blacksmith : ZaldoSofya City: Blacksmith",
        "item_prop": "Sell160 SpinaProcess80 Wood"
    },
    {
        "card_title": "4th Anniv Staff VIII[Staff]",
        "item_basestat": "Stat/EffectAmountBase ATK242Base Stability %60Potential41",
        "item_obtainfrom": "[Player]Smith Skill-",
        "item_prop": "Sell160 SpinaProcess80 Wood"
    },
    {
        "card_title": "5th Anniv Staff IV[Staff]",
        "item_basestat": "Stat/EffectAmountBase ATK242INT %6MaxMP550MATK %6Physical Resistance %30CSPD %35Base Stability %60",
        "item_obtainfrom": "[NPC]Blacksmith : ZaldoSofya City: Blacksmith",
        "item_prop": "Sell160 SpinaProcess80 Wood"
    },
    {
        "card_title": "5th Anniv Staff IV[Staff]",
        "item_basestat": "Stat/EffectAmountBase ATK242Base Stability %60Potential41",
        "item_obtainfrom": "[Player]Smith Skill-",
        "item_prop": "Sell160 SpinaProcess80 Wood"
    },
    {
        "card_title": "Spirit Staff[Staff]",
        "item_basestat": "Stat/EffectAmountBase ATK242VIT %5MaxHP %10MATK %6Ailment Resistance %5Light Element1Base Stability %60",
        "item_obtainfrom": "[NPC]Blacksmith : ZaldoSofya City: Blacksmith",
        "item_prop": "Sell160 SpinaProcess80 Wood"
    },
    {
        "card_title": "Spirit Staff[Staff]",
        "item_basestat": "Stat/EffectAmountBase ATK242Base Stability %60Potential41",
        "item_obtainfrom": "[Player]Smith Skill-",
        "item_prop": "Sell160 SpinaProcess80 Wood"
    },
    {
        "card_title": "Spirit Staff[Staff]",
        "item_basestat": "Stat/EffectAmountBase ATK242VIT %3MaxHP %10MATK %6Ailment Resistance %1Light Element1Base Stability %60",
        "item_obtainfrom": "Sand Bandits Potum(Lv 174)Geist Desert: Area 1",
        "item_prop": "Sell160 SpinaProcess80 Wood"
    },
    {
        "card_title": "Piton Staff[Staff]",
        "item_basestat": "Stat/EffectAmountBase ATK253MaxHP %10MATK %6Physical Resistance %10Fire resistance %10Water Element1Base Stability %60Physical Barrier1000MATK UP (STR %)100",
        "item_obtainfrom": "King Piton(Lv 153)Elf Mountains: Shrine",
        "item_prop": "Sell165 SpinaProcess82 Beast"
    },
    {
        "card_title": "Piton Staff[Staff]",
        "item_basestat": "Stat/EffectAmountBase ATK253MaxHP %5MATK %6Physical Resistance %10Fire resistance %15Water Element1Base Stability %60Physical Barrier1500MATK UP (STR %)75",
        "item_obtainfrom": "[NPC]Blacksmith : ZaldoSofya City: Blacksmith",
        "item_prop": "Sell165 SpinaProcess82 Beast"
    },
    {
        "card_title": "Piton Staff[Staff]",
        "item_basestat": "Stat/EffectAmountBase ATK253Base Stability %60Potential41",
        "item_obtainfrom": "[Player]Smith Skill-",
        "item_prop": "Sell165 SpinaProcess82 Beast"
    },
    {
        "card_title": "Shaman Staff[Staff]",
        "item_basestat": "Stat/EffectAmountBase ATK260MaxMP300MATK %6Dark Element1Base Stability %50Magic Barrier1200",
        "item_obtainfrom": "[NPC]Blacksmith : ZaldoSofya City: Blacksmith",
        "item_prop": "Sell150 SpinaProcess75 Wood"
    },
    {
        "card_title": "Shaman Staff[Staff]",
        "item_basestat": "Stat/EffectAmountBase ATK260Base Stability %50Potential39",
        "item_obtainfrom": "[Player]Smith Skill-",
        "item_prop": "Sell150 SpinaProcess75 Wood"
    },
    {
        "card_title": "Shaman Staff[Staff]",
        "item_basestat": "Stat/EffectAmountBase ATK260MaxMP200MATK %6Dark Element1Base Stability %50Magic Barrier1000",
        "item_obtainfrom": "Petally(Lv 158)Morthell Swell: Area 1",
        "item_prop": "Sell150 SpinaProcess75 Wood"
    },
    {
        "card_title": "Abracadabra Cone III[Staff]",
        "item_basestat": "Stat/EffectAmountBase ATK265MaxHP1500MaxMP300CSPD1000Water resistance %15Wind Element1Base Stability %60Guard Break %25",
        "item_obtainfrom": "[NPC]Blacksmith : ZaldoSofya City: Blacksmith",
        "item_prop": "Sell17 SpinaProcessunknown"
    },
    {
        "card_title": "Abracadabra Cone III[Staff]",
        "item_basestat": "Stat/EffectAmountBase ATK265Base Stability %60Potential41",
        "item_obtainfrom": "[Player]Smith Skill-",
        "item_prop": "Sell44 SpinaProcessunknown"
    },
    {
        "card_title": "Lightning Flame[Staff]",
        "item_basestat": "Stat/EffectAmountBase ATK265Magic Pierce %50CSPD750CSPD %25Base Stability %60Absolute Dodge %5",
        "item_obtainfrom": "Potumotter (11M DL)(Lv 160)Sofya City: Government Office",
        "item_prop": "Sell170 SpinaProcess85 Wood"
    },
    {
        "card_title": "Mana Cascade Staff[Staff]",
        "item_basestat": "Stat/EffectAmountBase ATK265MATK %6Stability %12CSPD %24Water Element1Base Stability %60",
        "item_obtainfrom": "[NPC]Blacksmith : ZaldoSofya City: Blacksmith",
        "item_prop": "SellUnknownProcessunknown"
    },
    {
        "card_title": "Mana Cascade Staff[Staff]",
        "item_basestat": "Stat/EffectAmountBase ATK265Base Stability %60Potential42",
        "item_obtainfrom": "[Player]Smith Skill-",
        "item_prop": "SellUnknownProcessunknown"
    },
    {
        "card_title": "Mana Cascade Staff[Staff]",
        "item_basestat": "Stat/EffectAmountBase ATK265MATK %6Stability %10CSPD %20Water Element1Base Stability %60",
        "item_obtainfrom": "Eerie Scarecrow(Lv 183)Witch's Woods Area 1",
        "item_prop": "Sell170 SpinaProcess85 Wood"
    },
    {
        "card_title": "Lovely Wand[Staff]",
        "item_basestat": "Stat/EffectAmountBase ATK272ATK %8Critical Rate %40% stronger against Fire-25% stronger against Dark25Attack MP Recovery16Base Stability %80Reflect %50Additional Melee %100Attack Range (m)2",
        "item_obtainfrom": "Garnache (Dark)(Lv 230)Creme Cliff (Valentine's Day Event)",
        "item_prop": "Sell200 SpinaProcess100 Mana"
    },
    {
        "card_title": "4th Anniv Staff IX[Staff]",
        "item_basestat": "Stat/EffectAmountBase ATK277INT %7MaxMP500MATK %7Physical Resistance %30CSPD %40Base Stability %60",
        "item_obtainfrom": "[NPC]Blacksmith : ZaldoSofya City: Blacksmith",
        "item_prop": "Sell175 SpinaProcess87 Wood"
    },
    {
        "card_title": "4th Anniv Staff IX[Staff]",
        "item_basestat": "Stat/EffectAmountBase ATK277Base Stability %60Potential43",
        "item_obtainfrom": "[Player]Smith Skill-",
        "item_prop": "Sell175 SpinaProcess87 Wood"
    },
    {
        "card_title": "5th Anniv Staff V[Staff]",
        "item_basestat": "Stat/EffectAmountBase ATK277INT %7MaxMP600MATK %7Physical Resistance %30CSPD %40Base Stability %60Reduce Dmg (Bullet) %2",
        "item_obtainfrom": "[NPC]Blacksmith : ZaldoSofya City: Blacksmith",
        "item_prop": "Sell175 SpinaProcess87 Wood"
    },
    {
        "card_title": "5th Anniv Staff V[Staff]",
        "item_basestat": "Stat/EffectAmountBase ATK277Base Stability %60Potential43",
        "item_obtainfrom": "[Player]Smith Skill-",
        "item_prop": "Sell175 SpinaProcess87 Wood"
    },
    {
        "card_title": "6th Anniv Staff IV[Staff]",
        "item_basestat": "Stat/EffectAmountBase ATK277INT %7MaxMP600MATK %7Physical Resistance %30CSPD %40Base Stability %60Reduce Dmg (Bullet) %4Knuckle only:Absolute Dodge %10",
        "item_obtainfrom": "[NPC]Blacksmith : ZaldoSofya City: Blacksmith",
        "item_prop": "Sell175 SpinaProcess87 Wood"
    },
    {
        "card_title": "6th Anniv Staff IV[Staff]",
        "item_basestat": "Stat/EffectAmountBase ATK277Base Stability %60Potential43",
        "item_obtainfrom": "[Player]Smith Skill-",
        "item_prop": "Sell175 SpinaProcess87 Wood"
    },
    {
        "card_title": "7th Anniv Staff III[Staff]",
        "item_basestat": "Stat/EffectAmountBase ATK277INT %7MATK %7Magic Pierce %14CSPD %56Critical Rate30Base Stability %60Reduce Dmg (Bullet) %30Attack Range (m)2",
        "item_obtainfrom": "[NPC]Blacksmith : ZaldoSofya City: Blacksmith",
        "item_prop": "Sell175 SpinaProcess87 Wood"
    },
    {
        "card_title": "7th Anniv Staff III[Staff]",
        "item_basestat": "Stat/EffectAmountBase ATK277Base Stability %60Potential43Attack Range (m)2",
        "item_obtainfrom": "[Player]Smith Skill-",
        "item_prop": "Sell175 SpinaProcess87 Wood"
    },
    {
        "card_title": "8th Anniv Staff II[Staff]",
        "item_basestat": "Stat/EffectAmountBase ATK277INT %7MATK %7Magic Pierce %15Critical Rate35Critical Rate %60Base Stability %60Reduce Dmg (Bullet) %35Attack Range (m)2",
        "item_obtainfrom": "[NPC]Blacksmith : ZaldoSofya City: Blacksmith",
        "item_prop": "Sell175 SpinaProcess87 Wood"
    },
    {
        "card_title": "8th Anniv Staff II[Staff]",
        "item_basestat": "Stat/EffectAmountBase ATK277Base Stability %60Potential43Attack Range (m)2",
        "item_obtainfrom": "[Player]Smith Skill-",
        "item_prop": "Sell175 SpinaProcess87 Wood"
    },
    {
        "card_title": "9th Anniv Staff[Staff]",
        "item_basestat": "Stat/EffectAmountBase ATK277INT %6MATK %7Magic Pierce %10CSPD %50Critical Rate40Base Stability %60Reduce Dmg (Bullet) %40Knuckle only:Physical Pierce %10",
        "item_obtainfrom": "[NPC]Blacksmith : Zaldo555Sofya City: Blacksmith",
        "item_prop": "Sell0 SpinaProcessunknown"
    },
    {
        "card_title": "9th Anniv Staff[Staff]",
        "item_basestat": "Stat/EffectAmountBase ATK277Base Stability %60Potential43",
        "item_obtainfrom": "[Player]Smith Skill555-",
        "item_prop": "Sell0 SpinaProcessunknown"
    },
    {
        "card_title": "Choco Parfait Staff[Staff]",
        "item_basestat": "Stat/EffectAmountBase ATK277INT %4MATK %6CSPD %-30Aggro %-15Fire Element1Long Range Damage %5Base Stability %55",
        "item_obtainfrom": "[NPC]Blacksmith : ZaldoSofya City: Blacksmith",
        "item_prop": "Sell180 SpinaProcess90 Mana"
    },
    {
        "card_title": "Seadevil Staff[Staff]",
        "item_basestat": "Stat/EffectAmountBase ATK277MaxHP3000MATK %6Light resistance %20Dark Element1Base Stability %60MATK UP (VIT %)100",
        "item_obtainfrom": "Adaro(Lv 160)Underwater Ruins: Deepest",
        "item_prop": "Sell1 SpinaProcess2 Mana"
    },
    {
        "card_title": "Seadevil Staff[Staff]",
        "item_basestat": "Stat/EffectAmountBase ATK277MaxHP6000MATK %8CSPD1000Light resistance %10Dark Element1Base Stability %60MATK UP (VIT %)100",
        "item_obtainfrom": "Adaro (High Difficulty)(Lv 200)Underwater Ruins: Deepest",
        "item_prop": "Sell1 SpinaProcess2 Mana"
    },
    {
        "card_title": "Staff of Cold Serenity[Staff]",
        "item_basestat": "Stat/EffectAmountBase ATK289MaxHP2000MATK %8CSPD %100% stronger against Water25Light resistance %-30Aggro %-30Water Element1Base Stability %70MATK UP (DEX %)100",
        "item_obtainfrom": "Yule Cat(Lv 197)Tomte Pavillion (170-190)",
        "item_prop": "SellUnknownProcessunknown"
    },
    {
        "card_title": "Jibril's Diary II[Staff]",
        "item_basestat": "Stat/EffectAmountBase ATK290MaxMP300MATK %7Magic Pierce %20Evasion Recharge %20Aggro %-50Dark Element1Base Stability %60Stun Unavailable1Absolute Dodge %10Reduce Dmg (Straight Line) %20% stronger against Neutral25",
        "item_obtainfrom": "empty",
        "item_prop": "Sell180 SpinaProcess2000 Mana"
    },
    {
        "card_title": "Mortal Slate[Staff]",
        "item_basestat": "Stat/EffectAmountBase ATK290MATK %7CSPD1000Ailment Resistance %5Wind Element1Base Stability %60Reduce Dmg (Bowling) %20",
        "item_obtainfrom": "Gravicep(Lv 174)Recetacula Sector: Depot Rooftop",
        "item_prop": "SellUnknownProcessunknown"
    },
    {
        "card_title": "Mortal Slate[Staff]",
        "item_basestat": "Stat/EffectAmountBase ATK290MATK %7CSPD300Ailment Resistance %5Wind Element1Base Stability %60Reduce Dmg (Bowling) %25",
        "item_obtainfrom": "[NPC]Blacksmith : ZaldoSofya City: Blacksmith",
        "item_prop": "Sell180 SpinaProcess90 Metal"
    },
    {
        "card_title": "Mortal Slate[Staff]",
        "item_basestat": "Stat/EffectAmountBase ATK290Base Stability %60Potential44",
        "item_obtainfrom": "[Player]Smith Skill-",
        "item_prop": "Sell180 SpinaProcess90 Metal"
    },
    {
        "card_title": "Vine Staff[Staff]",
        "item_basestat": "Stat/EffectAmountBase ATK290MaxHP6000MATK %7Critical Rate %-80Earth Element1Base Stability %60",
        "item_obtainfrom": "Dryanymon(Lv 196)Storage Yard: Area 1",
        "item_prop": "Sell180 SpinaProcess90 Wood"
    },
    {
        "card_title": "Vine Staff[Staff]",
        "item_basestat": "Stat/EffectAmountBase ATK290MaxHP7000MATK %7Critical Rate %-70Earth Element1Base Stability %60",
        "item_obtainfrom": "[NPC]Blacksmith : ZaldoSofya City: Blacksmith",
        "item_prop": "Sell180 SpinaProcess90 Wood"
    },
    {
        "card_title": "Vine Staff[Staff]",
        "item_basestat": "Stat/EffectAmountBase ATK290Base Stability %60Potential44",
        "item_obtainfrom": "[Player]Smith Skill-",
        "item_prop": "Sell180 SpinaProcess90 Wood"
    },
    {
        "card_title": "Iris Ark Staff[Staff]",
        "item_basestat": "Stat/EffectAmountBase ATK300Magic Pierce %12DEF %-25MDEF %-25Aggro %-30Water Element1Long Range Damage %6Base Stability %60Additional Melee %50Invincible Aid (sec)3",
        "item_obtainfrom": "Rainy Season EventEvent",
        "item_prop": "Sell180 SpinaProcess100 Mana"
    },
    {
        "card_title": "5th Anniv Staff VI[Staff]",
        "item_basestat": "Stat/EffectAmountBase ATK301INT %7MaxMP650MATK %7Physical Resistance %30CSPD %45Base Stability %60Reduce Dmg (Bullet) %4",
        "item_obtainfrom": "[NPC]Blacksmith : ZaldoSofya City: Blacksmith",
        "item_prop": "Sell185 SpinaProcess92 Wood"
    },
    {
        "card_title": "5th Anniv Staff VI[Staff]",
        "item_basestat": "Stat/EffectAmountBase ATK301Base Stability %60Potential45",
        "item_obtainfrom": "[Player]Smith Skill-",
        "item_prop": "Sell185 SpinaProcess92 Wood"
    },
    {
        "card_title": "Eternal Melody Staff[Staff]",
        "item_basestat": "Stat/EffectAmountBase ATK305Stability %10CSPD1000Critical Rate100Dark Element1Base Stability %60Guard Break %10",
        "item_obtainfrom": "[NPC]HATSUNE MIKU's Collab Event Reception (1st Part)HATSUNE MIKU Collab Venue",
        "item_prop": "Sell1 SpinaProcess100 Mana"
    },
    {
        "card_title": "Windchanter Staff[Staff]",
        "item_basestat": "Stat/EffectAmountBase ATK314Critical Rate %-30% stronger against Water5Wind Element1Long Range Damage %7Base Stability %60Attack Range (m)2",
        "item_obtainfrom": "Grigori(Lv 204)Arstida: Area 1",
        "item_prop": "Sell190 SpinaProcess95 Wood"
    },
    {
        "card_title": "Windchanter Staff[Staff]",
        "item_basestat": "Stat/EffectAmountBase ATK314Critical Rate %-15% stronger against Water5Wind Element1Long Range Damage %7Base Stability %60Attack Range (m)2",
        "item_obtainfrom": "[NPC]Blacksmith : ZaldoSofya City: Blacksmith",
        "item_prop": "Sell190 SpinaProcess95 Wood"
    },
    {
        "card_title": "Windchanter Staff[Staff]",
        "item_basestat": "Stat/EffectAmountBase ATK314Base Stability %60Potential45Attack Range (m)2",
        "item_obtainfrom": "[Player]Smith Skill-",
        "item_prop": "Sell190 SpinaProcess95 Wood"
    },
    {
        "card_title": "Pom Pom Staff Mace[Staff]",
        "item_basestat": "Stat/EffectAmountBase ATK318ATK %7MATK %7Light Element1Short Range Damage %7% stronger against Neutral30Base Stability %70Tumble Unavailable1",
        "item_obtainfrom": "Hero Potum Party (12M DL)(Lv 170)Archfiend's Throne",
        "item_prop": "Sell180 SpinaProcess90 Metal"
    },
    {
        "card_title": "5th Anniv Staff VII[Staff]",
        "item_basestat": "Stat/EffectAmountBase ATK327INT %7MaxMP700MATK %7Physical Resistance %30CSPD %50Base Stability %60Reduce Dmg (Bullet) %6",
        "item_obtainfrom": "[NPC]Blacksmith : ZaldoSofya City: Blacksmith",
        "item_prop": "Sell195 SpinaProcess97 Wood"
    },
    {
        "card_title": "5th Anniv Staff VII[Staff]",
        "item_basestat": "Stat/EffectAmountBase ATK327Base Stability %60Potential46",
        "item_obtainfrom": "[Player]Smith Skill-",
        "item_prop": "Sell195 SpinaProcess97 Wood"
    },
    {
        "card_title": "6th Anniv Staff V[Staff]",
        "item_basestat": "Stat/EffectAmountBase ATK327INT %7MaxMP700MATK %7Physical Resistance %30CSPD %50Base Stability %60Reduce Dmg (Bullet) %6Knuckle only:Absolute Dodge %10",
        "item_obtainfrom": "[NPC]Blacksmith : ZaldoSofya City: Blacksmith",
        "item_prop": "Sell195 SpinaProcess97 Wood"
    },
    {
        "card_title": "6th Anniv Staff V[Staff]",
        "item_basestat": "Stat/EffectAmountBase ATK327Base Stability %60Potential46",
        "item_obtainfrom": "[Player]Smith Skill-",
        "item_prop": "Sell195 SpinaProcess97 Wood"
    },
    {
        "card_title": "7th Anniv Staff IV[Staff]",
        "item_basestat": "Stat/EffectAmountBase ATK327INT %7MATK %7Magic Pierce %16CSPD %64Critical Rate30Base Stability %60Reduce Dmg (Bullet) %30Attack Range (m)2",
        "item_obtainfrom": "[NPC]Blacksmith : ZaldoSofya City: Blacksmith",
        "item_prop": "Sell195 SpinaProcess97 Wood"
    },
    {
        "card_title": "7th Anniv Staff IV[Staff]",
        "item_basestat": "Stat/EffectAmountBase ATK327Base Stability %60Potential46Attack Range (m)2",
        "item_obtainfrom": "[Player]Smith Skill-",
        "item_prop": "Sell195 SpinaProcess97 Wood"
    },
    {
        "card_title": "8th Anniv Staff III[Staff]",
        "item_basestat": "Stat/EffectAmountBase ATK327INT %7MATK %7Magic Pierce %20Critical Rate35Critical Rate %70Base Stability %60Reduce Dmg (Bullet) %35Attack Range (m)2",
        "item_obtainfrom": "[NPC]Blacksmith : ZaldoSofya City: Blacksmith",
        "item_prop": "Sell195 SpinaProcess97 Wood"
    },
    {
        "card_title": "8th Anniv Staff III[Staff]",
        "item_basestat": "Stat/EffectAmountBase ATK327Base Stability %60Potential46Attack Range (m)2",
        "item_obtainfrom": "[Player]Smith Skill-",
        "item_prop": "Sell195 SpinaProcess97 Wood"
    },
    {
        "card_title": "9th Anniv Staff II[Staff]",
        "item_basestat": "Stat/EffectAmountBase ATK327INT %7MATK %7Magic Pierce %13CSPD %55Critical Rate40Base Stability %60Reduce Dmg (Bullet) %40Knuckle only:Physical Pierce %11Magic Pierce %-2",
        "item_obtainfrom": "[NPC]Blacksmith : Zaldo555Sofya City: Blacksmith",
        "item_prop": "Sell0 SpinaProcessunknown"
    },
    {
        "card_title": "9th Anniv Staff II[Staff]",
        "item_basestat": "Stat/EffectAmountBase ATK327Base Stability %60Potential46",
        "item_obtainfrom": "[Player]Smith Skill555-",
        "item_prop": "Sell0 SpinaProcessunknown"
    },
    {
        "card_title": "Demon Empress Staff[Staff]",
        "item_basestat": "Stat/EffectAmountBase ATK327MATK %7Critical Rate25Fire Element1% stronger against Neutral25Base Stability %60Anticipate %15Dagger only:CSPD900",
        "item_obtainfrom": "Venena Metacoenubia(Lv 185)Neo Plastida",
        "item_prop": "SellUnknownProcessunknown"
    },
    {
        "card_title": "Demon Empress Staff[Staff]",
        "item_basestat": "Stat/EffectAmountBase ATK327MATK %7Critical Rate20Fire Element1% stronger against Neutral10Base Stability %60Anticipate %20Dagger only:CSPD1000",
        "item_obtainfrom": "[NPC]Blacksmith : ZaldoSofya City: Blacksmith",
        "item_prop": "Sell195 SpinaProcess97 Mana"
    },
    {
        "card_title": "Demon Empress Staff[Staff]",
        "item_basestat": "Stat/EffectAmountBase ATK327Base Stability %60Potential46",
        "item_obtainfrom": "[Player]Smith Skill-",
        "item_prop": "Sell195 SpinaProcess97 Mana"
    },
    {
        "card_title": "Sweet Spoon II[Staff]",
        "item_basestat": "Stat/EffectAmountBase ATK327MATK %7ASPD %-100% stronger against Neutral25Base Stability %60Physical Barrier1500",
        "item_obtainfrom": "Mercy (Choco Banana)(Lv 220)Dunkel Valley",
        "item_prop": "Sell1 SpinaProcess100 Mana"
    },
    {
        "card_title": "Eternal Melody Staff[Staff]",
        "item_basestat": "Stat/EffectAmountBase ATK340MATK %8Critical Rate20Critical Rate %20Earth resistance %20Fire Element1Base Stability %60Additional Magic %50Reduce Dmg (Meteor) %20",
        "item_obtainfrom": "[NPC]HATSUNE MIKU's Collab Event Reception (1st Part)HATSUNE MIKU Collab Venue",
        "item_prop": "Sell1 SpinaProcess100 Mana"
    },
    {
        "card_title": "Eternal Melody Staff[Staff]",
        "item_basestat": "Stat/EffectAmountBase ATK340MaxMP20MATK %8Light resistance %30Aggro %-40Dark Element1Base Stability %60Physical Barrier5000Reduce Dmg (Meteor) %30",
        "item_obtainfrom": "[NPC]HATSUNE MIKU's Collab Event Reception (1st Part)HATSUNE MIKU Collab Venue",
        "item_prop": "Sell1 SpinaProcess100 Mana"
    },
    {
        "card_title": "Eternal Melody Staff[Staff]",
        "item_basestat": "Stat/EffectAmountBase ATK340MaxMP20MATK %8Earth resistance %30Aggro %-40Fire Element1Base Stability %60Physical Barrier5000Reduce Dmg (Meteor) %30",
        "item_obtainfrom": "[NPC]HATSUNE MIKU's Collab Event Reception (1st Part)HATSUNE MIKU Collab Venue",
        "item_prop": "Sell1 SpinaProcess100 Mana"
    },
    {
        "card_title": "Eternal Melody Staff[Staff]",
        "item_basestat": "Stat/EffectAmountBase ATK340MaxMP600MATK %8Magic Pierce %30Light resistance %5Dark Element1Base Stability %60Physical Barrier1000Reduce Dmg (Meteor) %5",
        "item_obtainfrom": "[NPC]HATSUNE MIKU's Collab Event Reception (1st Part)HATSUNE MIKU Collab Venue",
        "item_prop": "Sell1 SpinaProcess100 Mana"
    },
    {
        "card_title": "Eternal Melody Staff[Staff]",
        "item_basestat": "Stat/EffectAmountBase ATK340MaxMP600MATK %8Magic Pierce %30Earth resistance %5Fire Element1Base Stability %60Physical Barrier1000Reduce Dmg (Meteor) %5",
        "item_obtainfrom": "[NPC]HATSUNE MIKU's Collab Event Reception (1st Part)HATSUNE MIKU Collab Venue",
        "item_prop": "Sell1 SpinaProcess100 Mana"
    },
    {
        "card_title": "Eternal Melody Staff[Staff]",
        "item_basestat": "Stat/EffectAmountBase ATK340INT %4MaxMP400MATK %8Light resistance %10Dark Element1Base Stability %60Physical Barrier3000Reduce Dmg (Meteor) %10",
        "item_obtainfrom": "[NPC]HATSUNE MIKU's Collab Event Reception (1st Part)HATSUNE MIKU Collab Venue",
        "item_prop": "Sell1 SpinaProcess100 Mana"
    },
    {
        "card_title": "Eternal Melody Staff[Staff]",
        "item_basestat": "Stat/EffectAmountBase ATK340INT %4MaxMP400MATK %8Earth resistance %10Fire Element1Base Stability %60Physical Barrier3000Reduce Dmg (Meteor) %10",
        "item_obtainfrom": "[NPC]HATSUNE MIKU's Collab Event Reception (1st Part)HATSUNE MIKU Collab Venue",
        "item_prop": "Sell1 SpinaProcess100 Mana"
    },
    {
        "card_title": "Eternal Melody Staff[Staff]",
        "item_basestat": "Stat/EffectAmountBase ATK340MATK %8Critical Rate20Critical Rate %20Light resistance %20Dark Element1Base Stability %60Additional Magic %50Reduce Dmg (Meteor) %20",
        "item_obtainfrom": "[NPC]HATSUNE MIKU's Collab Event Reception (1st Part)HATSUNE MIKU Collab Venue",
        "item_prop": "Sell1 SpinaProcess100 Mana"
    },
    {
        "card_title": "Ghoulfish War Hammer[Staff]",
        "item_basestat": "Stat/EffectAmountBase ATK340ATK %8Stability %30Physical Pierce %15CSPD500Attack MP Recovery20Base Stability %40Shield only:Physical Resistance %20",
        "item_obtainfrom": "Pisteus(Lv 183)Ducia Coast: Depths",
        "item_prop": "Sell195 SpinaProcess97 Metal"
    },
    {
        "card_title": "Ghoulfish War Hammer[Staff]",
        "item_basestat": "Stat/EffectAmountBase ATK340ATK %8Stability %20Physical Pierce %10CSPD1000Attack MP Recovery25Base Stability %40",
        "item_obtainfrom": "[NPC]Blacksmith : ZaldoSofya City: Blacksmith",
        "item_prop": "Sell195 SpinaProcess97 Metal"
    },
    {
        "card_title": "Ghoulfish War Hammer[Staff]",
        "item_basestat": "Stat/EffectAmountBase ATK340Base Stability %40Potential46",
        "item_obtainfrom": "[Player]Smith Skill-",
        "item_prop": "Sell195 SpinaProcess97 Metal"
    },
    {
        "card_title": "Luster Staff[Staff]",
        "item_basestat": "Stat/EffectAmountBase ATK340MaxMP500MATK %8% stronger against Dark5Light Element1Base Stability %60Attack Range (m)2",
        "item_obtainfrom": "[NPC]Blacksmith : ZaldoSofya City: Blacksmith",
        "item_prop": "SellUnknownProcessunknown"
    },
    {
        "card_title": "Luster Staff[Staff]",
        "item_basestat": "Stat/EffectAmountBase ATK340Base Stability %60Potential47Attack Range (m)2",
        "item_obtainfrom": "[Player]Smith Skill-",
        "item_prop": "SellUnknownProcessunknown"
    },
    {
        "card_title": "Luster Staff[Staff]",
        "item_basestat": "Stat/EffectAmountBase ATK340MaxMP400MATK %8% stronger against Dark5Light Element1Base Stability %60Attack Range (m)2",
        "item_obtainfrom": "Tarmuckus(Lv 217)Operation Zone: Residential Area",
        "item_prop": "Sell200 SpinaProcess100 Wood"
    },
    {
        "card_title": "Phantom Wisp Staff[Staff]",
        "item_basestat": "Stat/EffectAmountBase ATK340MATK %8Dodge100ASPD700Evasion Recharge %30Earth Element1Base Stability %60Absolute Dodge %5Light Armor only:Aggro %-50",
        "item_obtainfrom": "Phantom Wisp(Lv 200)Phantom Wisp's Hideout: Theater",
        "item_prop": "Sell200 SpinaProcess100 Metal"
    },
    {
        "card_title": "Shovel Staff[Staff]",
        "item_basestat": "Stat/EffectAmountBase ATK340STR %8MaxHP4000Physical Pierce %40Physical Resistance %20Magic Resistance %20Water Element1Base Stability %70Ninjutsu Scroll only:Ailment Resistance %20",
        "item_obtainfrom": "Snowball Event NPCSnowball Mini Game Venue",
        "item_prop": "SellUnknownProcessunknown"
    },
    {
        "card_title": "Yozakura Crescent Staff[Staff]",
        "item_basestat": "Stat/EffectAmountBase ATK340INT %2Accuracy300CSPD800% stronger against Dark10Light Element1Long Range Damage %6Base Stability %60Reduce Dmg (Bullet) %30",
        "item_obtainfrom": "[NPC]Blacksmith : ZaldoSofya City: Blacksmith",
        "item_prop": "Sell190 SpinaProcess95 Wood"
    },
    {
        "card_title": "Phillip's Microphone[Staff]",
        "item_basestat": "Stat/EffectAmountBase ATK347MaxHP2000MaxMP300CSPD1000Aggro %-75Base Stability %80",
        "item_obtainfrom": "[NPC]Pelulu (Eagle Talon Collab Event)Eagle Talon Collab Venue",
        "item_prop": "SellUnknownProcessunknown"
    },
    {
        "card_title": "Gemma Anello[Staff]",
        "item_basestat": "Stat/EffectAmountBase ATK353MaxMP400MATK %8Magic Resistance %20Neutral Resistance %20% stronger against Neutral30Base Stability %60Magic Barrier2000Magic Device only:Critical Rate30Aggro %-15",
        "item_obtainfrom": "Gemma(Lv 198)Fugitive Lake Swamp: Depths",
        "item_prop": "Sell205 SpinaProcess102 Mana"
    },
    {
        "card_title": "Gemma Anello[Staff]",
        "item_basestat": "Stat/EffectAmountBase ATK353MaxMP400MATK %8Magic Resistance %20Neutral Resistance %10% stronger against Neutral30Base Stability %60Magic Barrier1500",
        "item_obtainfrom": "[NPC]Blacksmith : ZaldoSofya City: Blacksmith",
        "item_prop": "Sell205 SpinaProcess102 Mana"
    },
    {
        "card_title": "Gemma Anello[Staff]",
        "item_basestat": "Stat/EffectAmountBase ATK353Base Stability %60Potential48",
        "item_obtainfrom": "[Player]Smith Skill-",
        "item_prop": "Sell205 SpinaProcess102 Mana"
    },
    {
        "card_title": "Ghost Candy Staff[Staff]",
        "item_basestat": "Stat/EffectAmountBase ATK353MATK %8Magic Pierce %20CSPD %-30% stronger against Water10Wind Element1Base Stability %70",
        "item_obtainfrom": "Neewollah (Easy)(Lv 150)Manor of Surprises: Grand Hall",
        "item_prop": "SellUnknownProcessunknown"
    },
    {
        "card_title": "6th Anniv Staff VI[Staff]",
        "item_basestat": "Stat/EffectAmountBase ATK367INT %8MaxMP700MATK %8Physical Resistance %30CSPD %60Base Stability %60Reduce Dmg (Bullet) %8Knuckle only:Absolute Dodge %10",
        "item_obtainfrom": "[NPC]Blacksmith : ZaldoSofya City: Blacksmith",
        "item_prop": "Sell210 SpinaProcess105 Wood"
    },
    {
        "card_title": "6th Anniv Staff VI[Staff]",
        "item_basestat": "Stat/EffectAmountBase ATK367Base Stability %60Potential49",
        "item_obtainfrom": "[Player]Smith Skill-",
        "item_prop": "Sell210 SpinaProcess105 Wood"
    },
    {
        "card_title": "7th Anniv Staff V[Staff]",
        "item_basestat": "Stat/EffectAmountBase ATK367INT %8MATK %8Magic Pierce %18CSPD %72Critical Rate30Base Stability %60Reduce Dmg (Bullet) %30Attack Range (m)2",
        "item_obtainfrom": "[NPC]Blacksmith : ZaldoSofya City: Blacksmith",
        "item_prop": "Sell210 SpinaProcess105 Wood"
    },
    {
        "card_title": "7th Anniv Staff V[Staff]",
        "item_basestat": "Stat/EffectAmountBase ATK367Base Stability %60Potential49Attack Range (m)2",
        "item_obtainfrom": "[Player]Smith Skill-",
        "item_prop": "Sell210 SpinaProcess105 Wood"
    },
    {
        "card_title": "8th Anniv Staff IV[Staff]",
        "item_basestat": "Stat/EffectAmountBase ATK367INT %8MATK %8Magic Pierce %20Critical Rate35Critical Rate %80Base Stability %60Reduce Dmg (Bullet) %35Attack Range (m)2",
        "item_obtainfrom": "[NPC]Blacksmith : ZaldoSofya City: Blacksmith",
        "item_prop": "Sell210 SpinaProcess105 Wood"
    },
    {
        "card_title": "8th Anniv Staff IV[Staff]",
        "item_basestat": "Stat/EffectAmountBase ATK367Base Stability %60Potential49Attack Range (m)2",
        "item_obtainfrom": "[Player]Smith Skill-",
        "item_prop": "Sell210 SpinaProcess105 Wood"
    },
    {
        "card_title": "9th Anniv Staff III[Staff]",
        "item_basestat": "Stat/EffectAmountBase ATK367INT %8MATK %8Magic Pierce %16CSPD %60Critical Rate40Base Stability %60Reduce Dmg (Bullet) %40Knuckle only:Physical Pierce %12Magic Pierce %-4",
        "item_obtainfrom": "[NPC]Blacksmith : Zaldo555Sofya City: Blacksmith",
        "item_prop": "Sell0 SpinaProcessunknown"
    },
    {
        "card_title": "9th Anniv Staff III[Staff]",
        "item_basestat": "Stat/EffectAmountBase ATK367Base Stability %60Potential49",
        "item_obtainfrom": "[Player]Smith Skill555-",
        "item_prop": "Sell0 SpinaProcessunknown"
    },
    {
        "card_title": "Beastlord Staff[Staff]",
        "item_basestat": "Stat/EffectAmountBase ATK367Base Stability %60Potential48",
        "item_obtainfrom": "[Player]Smith Skill-",
        "item_prop": "SellUnknownProcessunknown"
    },
    {
        "card_title": "Solar Staff[Staff]",
        "item_basestat": "Stat/EffectAmountBase ATK367Natural HP Regen %30Stability %17Magic Pierce %16CSPD %30Fire Element1Base Stability %60Attack Range (m)2",
        "item_obtainfrom": "Rosemee(Lv 225)Jabali Kubwa: Area 1",
        "item_prop": "Sell210 SpinaProcess105 Metal"
    },
    {
        "card_title": "Solar Staff[Staff]",
        "item_basestat": "Stat/EffectAmountBase ATK367Natural HP Regen %32Stability %16Magic Pierce %16CSPD %32Fire Element1Base Stability %60Attack Range (m)2",
        "item_obtainfrom": "[NPC]Blacksmith : ZaldoSofya City: Blacksmith",
        "item_prop": "Sell210 SpinaProcess105 Metal"
    },
    {
        "card_title": "Solar Staff[Staff]",
        "item_basestat": "Stat/EffectAmountBase ATK367Base Stability %60Potential49Attack Range (m)2",
        "item_obtainfrom": "[Player]Smith Skill-",
        "item_prop": "Sell210 SpinaProcess105 Metal"
    },
    {
        "card_title": "Pearl Sakura Staff[Staff]",
        "item_basestat": "Stat/EffectAmountBase ATK390MaxHP %30Critical Rate50Critical Rate %25% stronger against Earth10Aggro %-40Fire Element1Base Stability %60",
        "item_obtainfrom": "[NPC]Blacksmith : ZaldoSofya City: Blacksmith",
        "item_prop": "SellUnknownProcessWood"
    },
    {
        "card_title": "Queen of Hearts Staff[Staff]",
        "item_basestat": "Stat/EffectAmountBase ATK395MaxHP2000MaxMP400ASPD600CSPD1200% stronger against Light10Dark Element1",
        "item_obtainfrom": "[NPC]Blacksmith : ZaldoSofya City: Blacksmith",
        "item_prop": "Sell220 SpinaProcess110 Metal"
    },
    {
        "card_title": "Twisted Staff[Staff]",
        "item_basestat": "Stat/EffectAmountBase ATK395MaxMP800Magic Resistance %40Earth resistance %20Earth Element1Base Stability %60Attack Range (m)2",
        "item_obtainfrom": "Actilunia(Lv 241)Abandoned District: Area 1",
        "item_prop": "Sell220 SpinaProcess110 Wood"
    },
    {
        "card_title": "Xellos' Staff[Staff]",
        "item_basestat": "Stat/EffectAmountBase ATK395MATK %10Stability %20Magic Pierce %15ASPD1250CSPD %75Aggro %-40Dark Element1Base Stability %60Absolute Dodge %20Attack Range (m)2",
        "item_obtainfrom": "[NPC]Slayers: Collab Prize ExchangeSofya City",
        "item_prop": "Sell1000 SpinaProcessN/A"
    },
    {
        "card_title": "Cooling Fan[Staff]",
        "item_basestat": "Stat/EffectAmountBase ATK400MaxHP10000MaxMP500Ailment Resistance %25Water Element1Base Stability %60Invincible Aid (sec)1",
        "item_obtainfrom": "[NPC]Blacksmith : ZaldoSofya City: Blacksmith",
        "item_prop": "SellUnknownProcessunknown"
    },
    {
        "card_title": "Oculasignio Fan Staff[Staff]",
        "item_basestat": "Stat/EffectAmountBase ATK409MATK %9Magic Resistance %25% stronger against Light10Ailment Resistance %10Aggro %-30Dark Element1Base Stability %60Tumble Unavailable1",
        "item_obtainfrom": "Oculasignio(Lv 216)Mt. Vulcani: Summit",
        "item_prop": "SellUnknownProcessunknown"
    },
    {
        "card_title": "Oculasignio Fan Staff[Staff]",
        "item_basestat": "Stat/EffectAmountBase ATK409MATK %9Magic Resistance %30% stronger against Light10Ailment Resistance %5Aggro %-20Dark Element1Base Stability %60Tumble Unavailable1",
        "item_obtainfrom": "[NPC]Blacksmith : ZaldoSofya City: Blacksmith",
        "item_prop": "SellUnknownProcessunknown"
    },
    {
        "card_title": "Oculasignio Fan Staff[Staff]",
        "item_basestat": "Stat/EffectAmountBase ATK409Base Stability %60Potential51",
        "item_obtainfrom": "[Player]Smith Skill-",
        "item_prop": "SellUnknownProcessunknown"
    },
    {
        "card_title": "Reticencia[Staff]",
        "item_basestat": "Stat/EffectAmountBase ATK420Base Stability %60Fractional Barrier %25Guard Break %50Barrier Cooldown %25",
        "item_obtainfrom": "[NPC]Mysterious Exchange (P. Avatar 2022)Event",
        "item_prop": "Sell1 SpinaProcess1000 Mana"
    },
    {
        "card_title": "7th Anniv Staff VI[Staff]",
        "item_basestat": "Stat/EffectAmountBase ATK424INT %9MATK %9Magic Pierce %20CSPD %80Critical Rate30Base Stability %60Reduce Dmg (Bullet) %30Attack Range (m)2",
        "item_obtainfrom": "[NPC]Blacksmith : ZaldoSofya City: Blacksmith",
        "item_prop": "Sell230 SpinaProcess115 Wood"
    },
    {
        "card_title": "7th Anniv Staff VI[Staff]",
        "item_basestat": "Stat/EffectAmountBase ATK424Base Stability %60Potential52Attack Range (m)2",
        "item_obtainfrom": "[Player]Smith Skill-",
        "item_prop": "Sell230 SpinaProcess115 Wood"
    },
    {
        "card_title": "8th Anniv Staff V[Staff]",
        "item_basestat": "Stat/EffectAmountBase ATK424INT %9MATK %9Magic Pierce %25Critical Rate35Critical Rate %90Base Stability %60Reduce Dmg (Bullet) %35Attack Range (m)2",
        "item_obtainfrom": "[NPC]Blacksmith : ZaldoSofya City: Blacksmith",
        "item_prop": "Sell230 SpinaProcess115 Wood"
    },
    {
        "card_title": "8th Anniv Staff V[Staff]",
        "item_basestat": "Stat/EffectAmountBase ATK424Base Stability %60Potential52Attack Range (m)2",
        "item_obtainfrom": "[Player]Smith Skill-",
        "item_prop": "Sell230 SpinaProcess115 Wood"
    },
    {
        "card_title": "9th Anniv Staff IV[Staff]",
        "item_basestat": "Stat/EffectAmountBase ATK424INT %9MATK %9Magic Pierce %19CSPD %65Critical Rate40Reduce Dmg (Bullet) %40Knuckle only:Physical Pierce %13Magic Pierce %-6",
        "item_obtainfrom": "[NPC]Blacksmith : Zaldo555Sofya City: Blacksmith",
        "item_prop": "Sell0 SpinaProcessunknown"
    },
    {
        "card_title": "9th Anniv Staff IV[Staff]",
        "item_basestat": "Stat/EffectAmountBase ATK424Base Stability %60Potential52",
        "item_obtainfrom": "[Player]Smith Skill555-",
        "item_prop": "Sell0 SpinaProcessunknown"
    },
    {
        "card_title": "Eternal Melody Staff[Staff]",
        "item_basestat": "Stat/EffectAmountBase ATK424Stability %12CSPD1000Critical Rate125Dark Element1Base Stability %60Guard Break %15Attack Range (m)2",
        "item_obtainfrom": "[NPC]HATSUNE MIKU's Collab Event Reception: 1st Part (2023)HATSUNE MIKU Collab Venue",
        "item_prop": "Sell1 SpinaProcess100 Mana"
    },
    {
        "card_title": "Potum Staff[Staff]",
        "item_basestat": "Stat/EffectAmountBase ATK424MaxMP300Magic Pierce %30CSPD300Neutral Resistance %30% stronger against Neutral30Base Stability %80",
        "item_obtainfrom": "Hero Potum Party (13M DL)(Lv 190)Archfiend's Throne",
        "item_prop": "SellUnknownProcessunknown"
    },
    {
        "card_title": "Sphere Staff[Staff]",
        "item_basestat": "Stat/EffectAmountBase ATK424MATK %9ASPD500CSPD %50Wind Element1Base Stability %60Attack Range (m)2",
        "item_obtainfrom": "Terratulin(Lv 252)Eumano Village Ruins: Area 1",
        "item_prop": "Sell230 SpinaProcess115 Wood"
    },
    {
        "card_title": "Edgy Nova (Magic)[Staff]",
        "item_basestat": "Stat/EffectAmountBase ATK430MaxMP1000Aggro %-75Light Element1% stronger against Neutral35Base Stability %60Additional Magic %200Reduce Dmg (Foe Epicenter) %25Dagger only:CSPD %100",
        "item_obtainfrom": "Stellar Ooze(Lv 230)Event",
        "item_prop": "Sell230 SpinaProcess15 Metal"
    },
    {
        "card_title": "Rolling Pin Staff[Staff]",
        "item_basestat": "Stat/EffectAmountBase ATK444MaxHP8000MATK %10Physical Resistance %25Magic Resistance %20Motion Speed %5% stronger against Neutral35Base Stability %70Guard Break %15",
        "item_obtainfrom": "Mage Filecia (Plain)(Lv 190)El Scaro: Back Alley",
        "item_prop": "SellUnknownProcessunknown"
    },
    {
        "card_title": "Sakura Warrior Staff[Staff]",
        "item_basestat": "Stat/EffectAmountBase ATK454MaxMP800Stability %3Light Element1Short Range Damage %7Base Stability %60Attack Range (m)2Dagger only:Magic Pierce %25Tumble Unavailable1",
        "item_obtainfrom": "Baavgai (Easy)(Lv 200)Mt. Sakuraten: Summit",
        "item_prop": "Sell240 SpinaProcess120 Mana"
    },
    {
        "card_title": "Sakura Warrior Staff[Staff]",
        "item_basestat": "Stat/EffectAmountBase ATK454MaxMP800Stability %5Light Element1Short Range Damage %8Base Stability %60Attack Range (m)2Dagger only:Magic Pierce %25Tumble Unavailable1",
        "item_obtainfrom": "Baavgai (Normal)(Lv 220)Mt. Sakuraten: Summit",
        "item_prop": "Sell240 SpinaProcess120 Mana"
    },
    {
        "card_title": "Sakura Warrior Staff[Staff]",
        "item_basestat": "Stat/EffectAmountBase ATK454MaxMP800Stability %7Light Element1Short Range Damage %9Base Stability %60Attack Range (m)2Dagger only:Magic Pierce %25Tumble Unavailable1",
        "item_obtainfrom": "Baavgai (Hard)(Lv 240)Mt. Sakuraten: Summit",
        "item_prop": "Sell240 SpinaProcess120 Mana"
    },
    {
        "card_title": "Evil Aristo Staff[Staff]",
        "item_basestat": "Stat/EffectAmountBase ATK469MaxHP10000MATK %9Physical Resistance %15Critical Rate75Dark resistance %30Ailment Resistance %15Fire Element1Base Stability %60Attack Range (m)2Shield only:Aggro %50",
        "item_obtainfrom": "Wicked Dragon Fazzino(Lv 234)Propulsion System Room",
        "item_prop": "Sell245 SpinaProcess122 Metal"
    },
    {
        "card_title": "Evil Aristo Staff[Staff]",
        "item_basestat": "Stat/EffectAmountBase ATK469MaxHP7500MATK %9Physical Resistance %10Critical Rate75Dark resistance %40Ailment Resistance %10Fire Element1Base Stability %60Attack Range (m)2",
        "item_obtainfrom": "[NPC]Blacksmith : ZaldoSofya City: Blacksmith",
        "item_prop": "Sell245 SpinaProcess122 Metal"
    },
    {
        "card_title": "Evil Aristo Staff[Staff]",
        "item_basestat": "Stat/EffectAmountBase ATK469Base Stability %60Potential54Attack Range (m)2",
        "item_obtainfrom": "[Player]Smith Skill-",
        "item_prop": "Sell245 SpinaProcess122 Metal"
    },
    {
        "card_title": "8th Anniv Staff VI[Staff]",
        "item_basestat": "Stat/EffectAmountBase ATK485INT %10MATK %10Magic Pierce %25Critical Rate35Critical Rate %100Base Stability %60Reduce Dmg (Bullet) %35Attack Range (m)2",
        "item_obtainfrom": "[NPC]Blacksmith : ZaldoSofya City: Blacksmith",
        "item_prop": "Sell250 SpinaProcess125 Wood"
    },
    {
        "card_title": "8th Anniv Staff VI[Staff]",
        "item_basestat": "Stat/EffectAmountBase ATK485Base Stability %60Potential55Attack Range (m)2",
        "item_obtainfrom": "[Player]Smith Skill-",
        "item_prop": "Sell250 SpinaProcess125 Wood"
    },
    {
        "card_title": "9th Anniv Staff V[Staff]",
        "item_basestat": "Stat/EffectAmountBase ATK485INT %10MATK %10Magic Pierce %22CSPD %70Critical Rate40Base Stability %60Reduce Dmg (Bullet) %40Knuckle only:Physical Pierce %14Magic Pierce %-8",
        "item_obtainfrom": "[NPC]Blacksmith : Zaldo555Sofya City: Blacksmith",
        "item_prop": "Sell0 SpinaProcessunknown"
    },
    {
        "card_title": "9th Anniv Staff V[Staff]",
        "item_basestat": "Stat/EffectAmountBase ATK485Base Stability %60Potential60",
        "item_obtainfrom": "[Player]Smith Skill555-",
        "item_prop": "Sell0 SpinaProcessunknown"
    },
    {
        "card_title": "Eternal Melody Staff[Staff]",
        "item_basestat": "Stat/EffectAmountBase ATK485MATK %10Critical Rate40Critical Rate %40Earth resistance %25Fire Element1Base Stability %60Additional Magic %100Reduce Dmg (Meteor) %25Attack Range (m)2",
        "item_obtainfrom": "[NPC]HATSUNE MIKU's Collab Event Reception: 1st Part (2023)HATSUNE MIKU Collab Venue",
        "item_prop": "Sell1 SpinaProcess100 Mana"
    },
    {
        "card_title": "Eternal Melody Staff[Staff]",
        "item_basestat": "Stat/EffectAmountBase ATK485MATK %10Critical Rate40Critical Rate %40Light resistance %25Dark Element1Base Stability %60Additional Magic %10Reduce Dmg (Meteor) %25Attack Range (m)2",
        "item_obtainfrom": "[NPC]HATSUNE MIKU's Collab Event Reception: 1st Part (2023)HATSUNE MIKU Collab Venue",
        "item_prop": "Sell1 SpinaProcess100 Mana"
    },
    {
        "card_title": "Eternal Melody Staff[Staff]",
        "item_basestat": "Stat/EffectAmountBase ATK485MaxMP200MATK %9Earth resistance %35Aggro %-60Fire Element1Base Stability %60Physical Barrier6000Reduce Dmg (Meteor) %35Attack Range (m)2",
        "item_obtainfrom": "[NPC]HATSUNE MIKU's Collab Event Reception: 1st Part (2023)HATSUNE MIKU Collab Venue",
        "item_prop": "Sell1 SpinaProcess100 Mana"
    },
    {
        "card_title": "Eternal Melody Staff[Staff]",
        "item_basestat": "Stat/EffectAmountBase ATK485MaxMP200MATK %9Light resistance %35Aggro %-60Dark Element1Base Stability %60Physical Barrier6000Reduce Dmg (Meteor) %35Attack Range (m)2",
        "item_obtainfrom": "[NPC]HATSUNE MIKU's Collab Event Reception: 1st Part (2023)HATSUNE MIKU Collab Venue",
        "item_prop": "Sell1 SpinaProcess100 Mana"
    },
    {
        "card_title": "Eternal Melody Staff[Staff]",
        "item_basestat": "Stat/EffectAmountBase ATK485MaxMP600MATK %10Magic Pierce %30Earth resistance %10Fire Element1Base Stability %60Physical Barrier2000Reduce Dmg (Meteor) %10Attack Range (m)2",
        "item_obtainfrom": "[NPC]HATSUNE MIKU's Collab Event Reception: 1st Part (2023)HATSUNE MIKU Collab Venue",
        "item_prop": "Sell1 SpinaProcess100 Mana"
    },
    {
        "card_title": "Eternal Melody Staff[Staff]",
        "item_basestat": "Stat/EffectAmountBase ATK485MaxMP600MATK %10Magic Pierce %30Light resistance %10Dark Element1Base Stability %60Physical Barrier2000Reduce Dmg (Meteor) %10Attack Range (m)2",
        "item_obtainfrom": "[NPC]HATSUNE MIKU's Collab Event Reception: 1st Part (2023)HATSUNE MIKU Collab Venue",
        "item_prop": "Sell1 SpinaProcess100 Mana"
    },
    {
        "card_title": "Eternal Melody Staff[Staff]",
        "item_basestat": "Stat/EffectAmountBase ATK485INT %5MaxMP400MATK %10Earth resistance %15Fire Element1Base Stability %60Physical Barrier4000Reduce Dmg (Meteor) %15Attack Range (m)2",
        "item_obtainfrom": "[NPC]HATSUNE MIKU's Collab Event Reception: 1st Part (2023)HATSUNE MIKU Collab Venue",
        "item_prop": "Sell1 SpinaProcess100 Mana"
    },
    {
        "card_title": "Eternal Melody Staff[Staff]",
        "item_basestat": "Stat/EffectAmountBase ATK485INT %5MaxMP400MATK %10Light resistance %15Dark Element1Base Stability %60Physical Barrier4000Reduce Dmg (Meteor) %15Attack Range (m)2",
        "item_obtainfrom": "[NPC]HATSUNE MIKU's Collab Event Reception: 1st Part (2023)HATSUNE MIKU Collab Venue",
        "item_prop": "Sell1 SpinaProcess100 Mana"
    },
    {
        "card_title": "Reticencia[Staff]",
        "item_basestat": "Stat/EffectAmountBase ATK485Base Stability %60Fractional Barrier %25Guard Break %50Barrier Cooldown %25",
        "item_obtainfrom": "[NPC]Mysterious Exchange (P. Avatar 2023)Event",
        "item_prop": "Sell1 SpinaProcess1000 Mana"
    },
    {
        "card_title": "Amnis Staff[Staff]",
        "item_basestat": "Stat/EffectAmountBase ATK517Magic Pierce %40Critical Rate120Aggro %-100Water Element1Base Stability %50Shield only:Magic Resistance %30Ailment Resistance %15Aggro %100",
        "item_obtainfrom": "Red Ash Dragon Rudis(Lv 249)Espuma Dome: Entrance",
        "item_prop": "Sell260 SpinaProcess130 Metal"
    },
    {
        "card_title": "Amnis Staff[Staff]",
        "item_basestat": "Stat/EffectAmountBase ATK517Magic Pierce %40Critical Rate80Aggro %-20Water Element1Base Stability %50Shield only:Magic Resistance %45Ailment Resistance %15Aggro %20",
        "item_obtainfrom": "[NPC]Blacksmith : ZaldoSofya City: Blacksmith",
        "item_prop": "Sell0 SpinaProcessunknown"
    },
    {
        "card_title": "Amnis Staff[Staff]",
        "item_basestat": "Stat/EffectAmountBase ATK517Base Stability %50Potential57",
        "item_obtainfrom": "[Player]Smith Skill-",
        "item_prop": "Sell0 SpinaProcessunknown"
    },
    {
        "card_title": "9th Anniv Staff VI[Staff]",
        "item_basestat": "Stat/EffectAmountBase ATK550INT %10MATK %11Magic Pierce %25CSPD %75Critical Rate40Base Stability %60Reduce Dmg (Bullet) %40Knuckle only:Physical Pierce %15Magic Pierce %-10",
        "item_obtainfrom": "[NPC]Blacksmith : Zaldo555Sofya City: Blacksmith",
        "item_prop": "Sell0 SpinaProcessunknown"
    },
    {
        "card_title": "9th Anniv Staff VI[Staff]",
        "item_basestat": "Stat/EffectAmountBase ATK550Base Stability %60Potential59",
        "item_obtainfrom": "[Player]Smith Skill555-",
        "item_prop": "Sell0 SpinaProcessunknown"
    },
    {
        "card_title": "Gloomy Flower Staff[Staff]",
        "item_basestat": "Stat/EffectAmountBase ATK567MATK %11Dodge %110CSPD1100Earth Element1Long Range Damage %11Base Stability %60Additional Magic %110MATK UP (AGI %)100Reduce Dmg (Floor) %25",
        "item_obtainfrom": "Deformis(Lv 264)Eumano Village Ruins: Central",
        "item_prop": "Sell275 SpinaProcess137 Wood"
    },
    {
        "card_title": "Jibril's Diary III[Staff]",
        "item_basestat": "Stat/EffectAmountBase ATK580MaxMP300MATK %9Magic Pierce %20Evasion Recharge %40Aggro %-50Dark Element1Base Stability %60Stun Unavailable1Absolute Dodge %10Reduce Dmg (Straight Line) %30% stronger against Neutral30",
        "item_obtainfrom": "empty",
        "item_prop": "Sell280 SpinaProcess3000 Mana"
    }
]